[{"Id":210098,"Class":"1","Title":null,"ISSN":null,"Review":false,"Eidtions":null},{"Id":210131,"Class":"1","Title":null,"ISSN":null,"Review":false,"Eidtions":null},{"Id":210136,"Class":"1","Title":null,"ISSN":null,"Review":false,"Eidtions":null},{"Id":210208,"Class":"1","Title":null,"ISSN":null,"Review":false,"Eidtions":null},{"Id":210209,"Class":"2","Title":null,"ISSN":null,"Review":false,"Eidtions":null},{"Id":210273,"Class":"1","Title":null,"ISSN":null,"Review":false,"Eidtions":null},{"Id":210274,"Class":"1","Title":null,"ISSN":null,"Review":false,"Eidtions":null},{"Id":210283,"Class":"1","Title":null,"ISSN":null,"Review":false,"Eidtions":null},{"Id":210290,"Class":"1","Title":null,"ISSN":null,"Review":false,"Eidtions":null},{"Id":210294,"Class":"1","Title":null,"ISSN":null,"Review":false,"Eidtions":null},{"Id":210311,"Class":"2","Title":null,"ISSN":null,"Review":false,"Eidtions":null},{"Id":210322,"Class":"2","Title":null,"ISSN":null,"Review":false,"Eidtions":null},{"Id":210336,"Class":"1","Title":null,"ISSN":null,"Review":false,"Eidtions":null},{"Id":210365,"Class":"1","Title":null,"ISSN":null,"Review":false,"Eidtions":null},{"Id":210373,"Class":"1","Title":null,"ISSN":null,"Review":false,"Eidtions":null},{"Id":210376,"Class":"1","Title":null,"ISSN":null,"Review":false,"Eidtions":null},{"Id":210388,"Class":"1","Title":null,"ISSN":null,"Review":false,"Eidtions":null},{"Id":210391,"Class":"2","Title":null,"ISSN":null,"Review":false,"Eidtions":null},{"Id":210397,"Class":"2","Title":null,"ISSN":null,"Review":false,"Eidtions":null},{"Id":210412,"Class":"1","Title":null,"ISSN":null,"Review":false,"Eidtions":null},{"Id":210413,"Class":"1","Title":null,"ISSN":null,"Review":false,"Eidtions":null},{"Id":210482,"Class":"1","Title":null,"ISSN":null,"Review":false,"Eidtions":null},{"Id":210489,"Class":"2","Title":null,"ISSN":null,"Review":false,"Eidtions":null},{"Id":210513,"Class":"1","Title":null,"ISSN":null,"Review":false,"Eidtions":null},{"Id":210536,"Class":"1","Title":null,"ISSN":null,"Review":false,"Eidtions":null},{"Id":210537,"Class":"2","Title":null,"ISSN":null,"Review":false,"Eidtions":null},{"Id":210543,"Class":"2","Title":null,"ISSN":null,"Review":false,"Eidtions":null},{"Id":210577,"Class":"1","Title":null,"ISSN":null,"Review":false,"Eidtions":null},{"Id":210620,"Class":"3","Title":null,"ISSN":null,"Review":false,"Eidtions":null},{"Id":210629,"Class":"1","Title":null,"ISSN":null,"Review":false,"Eidtions":null},{"Id":210638,"Class":"2","Title":null,"ISSN":null,"Review":false,"Eidtions":null},{"Id":210653,"Class":"1","Title":null,"ISSN":null,"Review":false,"Eidtions":null},{"Id":210677,"Class":"1","Title":null,"ISSN":null,"Review":false,"Eidtions":null},{"Id":210770,"Class":"1","Title":null,"ISSN":null,"Review":false,"Eidtions":null},{"Id":210778,"Class":"2","Title":null,"ISSN":null,"Review":false,"Eidtions":null},{"Id":210780,"Class":"1","Title":null,"ISSN":null,"Review":false,"Eidtions":null},{"Id":210783,"Class":"1","Title":null,"ISSN":null,"Review":false,"Eidtions":null},{"Id":210800,"Class":"1","Title":null,"ISSN":null,"Review":false,"Eidtions":null},{"Id":210801,"Class":"3","Title":null,"ISSN":null,"Review":false,"Eidtions":null},{"Id":210813,"Class":"1","Title":null,"ISSN":null,"Review":false,"Eidtions":null},{"Id":210830,"Class":"1","Title":null,"ISSN":null,"Review":false,"Eidtions":null},{"Id":210833,"Class":"1","Title":null,"ISSN":null,"Review":false,"Eidtions":null},{"Id":210841,"Class":"1","Title":null,"ISSN":null,"Review":false,"Eidtions":null},{"Id":210858,"Class":"4","Title":null,"ISSN":null,"Review":false,"Eidtions":null},{"Id":210862,"Class":"2","Title":null,"ISSN":null,"Review":false,"Eidtions":null},{"Id":210887,"Class":"2","Title":null,"ISSN":null,"Review":false,"Eidtions":null},{"Id":210901,"Class":"2","Title":null,"ISSN":null,"Review":false,"Eidtions":null},{"Id":210910,"Class":"1","Title":null,"ISSN":null,"Review":false,"Eidtions":null},{"Id":210915,"Class":"1","Title":null,"ISSN":null,"Review":false,"Eidtions":null},{"Id":210920,"Class":"2","Title":null,"ISSN":null,"Review":false,"Eidtions":null},{"Id":210925,"Class":"3","Title":null,"ISSN":null,"Review":false,"Eidtions":null},{"Id":210927,"Class":"1","Title":null,"ISSN":null,"Review":false,"Eidtions":null},{"Id":210934,"Class":"2","Title":null,"ISSN":null,"Review":false,"Eidtions":null},{"Id":210946,"Class":"2","Title":null,"ISSN":null,"Review":false,"Eidtions":null},{"Id":210949,"Class":"2","Title":null,"ISSN":null,"Review":false,"Eidtions":null},{"Id":210965,"Class":"1","Title":null,"ISSN":null,"Review":false,"Eidtions":null},{"Id":210968,"Class":"1","Title":null,"ISSN":null,"Review":false,"Eidtions":null},{"Id":210993,"Class":"1","Title":null,"ISSN":null,"Review":false,"Eidtions":null},{"Id":210995,"Class":"2","Title":null,"ISSN":null,"Review":false,"Eidtions":null},{"Id":211027,"Class":"2","Title":null,"ISSN":null,"Review":false,"Eidtions":null},{"Id":211090,"Class":"1","Title":null,"ISSN":null,"Review":false,"Eidtions":null},{"Id":211099,"Class":"2","Title":null,"ISSN":null,"Review":false,"Eidtions":null},{"Id":211103,"Class":"1","Title":null,"ISSN":null,"Review":false,"Eidtions":null},{"Id":211112,"Class":"1","Title":null,"ISSN":null,"Review":false,"Eidtions":null},{"Id":211126,"Class":"1","Title":null,"ISSN":null,"Review":false,"Eidtions":null},{"Id":211160,"Class":"2","Title":null,"ISSN":null,"Review":false,"Eidtions":null},{"Id":211174,"Class":"3","Title":null,"ISSN":null,"Review":false,"Eidtions":null},{"Id":211186,"Class":"2","Title":null,"ISSN":null,"Review":false,"Eidtions":null},{"Id":211187,"Class":"2","Title":null,"ISSN":null,"Review":false,"Eidtions":null},{"Id":211275,"Class":"1","Title":null,"ISSN":null,"Review":false,"Eidtions":null},{"Id":211280,"Class":"3","Title":null,"ISSN":null,"Review":false,"Eidtions":null},{"Id":211308,"Class":"2","Title":null,"ISSN":null,"Review":false,"Eidtions":null},{"Id":211310,"Class":"2","Title":null,"ISSN":null,"Review":false,"Eidtions":null},{"Id":211314,"Class":"2","Title":null,"ISSN":null,"Review":false,"Eidtions":null},{"Id":211316,"Class":"2","Title":null,"ISSN":null,"Review":false,"Eidtions":null},{"Id":211318,"Class":"3","Title":null,"ISSN":null,"Review":false,"Eidtions":null},{"Id":211319,"Class":"2","Title":null,"ISSN":null,"Review":false,"Eidtions":null},{"Id":211324,"Class":"2","Title":null,"ISSN":null,"Review":false,"Eidtions":null},{"Id":211338,"Class":"1","Title":null,"ISSN":null,"Review":false,"Eidtions":null},{"Id":211351,"Class":"3","Title":null,"ISSN":null,"Review":false,"Eidtions":null},{"Id":211401,"Class":"3","Title":null,"ISSN":null,"Review":false,"Eidtions":null},{"Id":211415,"Class":"2","Title":null,"ISSN":null,"Review":false,"Eidtions":null},{"Id":211423,"Class":"1","Title":null,"ISSN":null,"Review":false,"Eidtions":null},{"Id":211480,"Class":"2","Title":null,"ISSN":null,"Review":false,"Eidtions":null},{"Id":211498,"Class":"2","Title":null,"ISSN":null,"Review":false,"Eidtions":null},{"Id":211510,"Class":"4","Title":null,"ISSN":null,"Review":false,"Eidtions":null},{"Id":211514,"Class":"4","Title":null,"ISSN":null,"Review":false,"Eidtions":null},{"Id":211519,"Class":"3","Title":null,"ISSN":null,"Review":false,"Eidtions":null},{"Id":211545,"Class":"1","Title":null,"ISSN":null,"Review":false,"Eidtions":null},{"Id":211582,"Class":"2","Title":null,"ISSN":null,"Review":false,"Eidtions":null},{"Id":211590,"Class":"3","Title":null,"ISSN":null,"Review":false,"Eidtions":null},{"Id":211596,"Class":"2","Title":null,"ISSN":null,"Review":false,"Eidtions":null},{"Id":211642,"Class":"3","Title":null,"ISSN":null,"Review":false,"Eidtions":null},{"Id":211667,"Class":"2","Title":null,"ISSN":null,"Review":false,"Eidtions":null},{"Id":211816,"Class":"2","Title":null,"ISSN":null,"Review":false,"Eidtions":null},{"Id":211836,"Class":"3","Title":null,"ISSN":null,"Review":false,"Eidtions":null},{"Id":211838,"Class":"2","Title":null,"ISSN":null,"Review":false,"Eidtions":null},{"Id":211870,"Class":"2","Title":null,"ISSN":null,"Review":false,"Eidtions":null},{"Id":211894,"Class":"2","Title":null,"ISSN":null,"Review":false,"Eidtions":null},{"Id":211911,"Class":"3","Title":null,"ISSN":null,"Review":false,"Eidtions":null},{"Id":211956,"Class":"2","Title":null,"ISSN":null,"Review":false,"Eidtions":null},{"Id":211978,"Class":"3","Title":null,"ISSN":null,"Review":false,"Eidtions":null},{"Id":212046,"Class":"3","Title":null,"ISSN":null,"Review":false,"Eidtions":null},{"Id":212069,"Class":"3","Title":null,"ISSN":null,"Review":false,"Eidtions":null},{"Id":212085,"Class":"3","Title":null,"ISSN":null,"Review":false,"Eidtions":null},{"Id":212091,"Class":"3","Title":null,"ISSN":null,"Review":false,"Eidtions":null},{"Id":212116,"Class":"2","Title":null,"ISSN":null,"Review":false,"Eidtions":null},{"Id":212146,"Class":"2","Title":null,"ISSN":null,"Review":false,"Eidtions":null},{"Id":212147,"Class":"4","Title":null,"ISSN":null,"Review":false,"Eidtions":null},{"Id":212182,"Class":"2","Title":null,"ISSN":null,"Review":false,"Eidtions":null},{"Id":212218,"Class":"3","Title":null,"ISSN":null,"Review":false,"Eidtions":null},{"Id":212222,"Class":"2","Title":null,"ISSN":null,"Review":false,"Eidtions":null},{"Id":212240,"Class":"2","Title":null,"ISSN":null,"Review":false,"Eidtions":null},{"Id":212243,"Class":"3","Title":null,"ISSN":null,"Review":false,"Eidtions":null},{"Id":212250,"Class":"2","Title":null,"ISSN":null,"Review":false,"Eidtions":null},{"Id":212269,"Class":"2","Title":null,"ISSN":null,"Review":false,"Eidtions":null},{"Id":212276,"Class":"2","Title":null,"ISSN":null,"Review":false,"Eidtions":null},{"Id":212286,"Class":"3","Title":null,"ISSN":null,"Review":false,"Eidtions":null},{"Id":212294,"Class":"2","Title":null,"ISSN":null,"Review":false,"Eidtions":null},{"Id":212297,"Class":"2","Title":null,"ISSN":null,"Review":false,"Eidtions":null},{"Id":212400,"Class":"3","Title":null,"ISSN":null,"Review":false,"Eidtions":null},{"Id":212423,"Class":"3","Title":null,"ISSN":null,"Review":false,"Eidtions":null},{"Id":212450,"Class":"3","Title":null,"ISSN":null,"Review":false,"Eidtions":null},{"Id":212461,"Class":"4","Title":null,"ISSN":null,"Review":false,"Eidtions":null},{"Id":212496,"Class":"2","Title":null,"ISSN":null,"Review":false,"Eidtions":null},{"Id":212504,"Class":"2","Title":null,"ISSN":null,"Review":false,"Eidtions":null},{"Id":212505,"Class":"1","Title":null,"ISSN":null,"Review":false,"Eidtions":null},{"Id":212579,"Class":"2","Title":null,"ISSN":null,"Review":false,"Eidtions":null},{"Id":212625,"Class":"3","Title":null,"ISSN":null,"Review":false,"Eidtions":null},{"Id":212656,"Class":"3","Title":null,"ISSN":null,"Review":false,"Eidtions":null},{"Id":212669,"Class":"2","Title":null,"ISSN":null,"Review":false,"Eidtions":null},{"Id":212675,"Class":"4","Title":null,"ISSN":null,"Review":false,"Eidtions":null},{"Id":212678,"Class":"4","Title":null,"ISSN":null,"Review":false,"Eidtions":null},{"Id":212688,"Class":"2","Title":null,"ISSN":null,"Review":false,"Eidtions":null},{"Id":212728,"Class":"4","Title":null,"ISSN":null,"Review":false,"Eidtions":null},{"Id":212759,"Class":"3","Title":null,"ISSN":null,"Review":false,"Eidtions":null},{"Id":212774,"Class":"4","Title":null,"ISSN":null,"Review":false,"Eidtions":null},{"Id":212831,"Class":"3","Title":null,"ISSN":null,"Review":false,"Eidtions":null},{"Id":212844,"Class":"2","Title":null,"ISSN":null,"Review":false,"Eidtions":null},{"Id":212861,"Class":"2","Title":null,"ISSN":null,"Review":false,"Eidtions":null},{"Id":212866,"Class":"2","Title":null,"ISSN":null,"Review":false,"Eidtions":null},{"Id":212874,"Class":"3","Title":null,"ISSN":null,"Review":false,"Eidtions":null},{"Id":212890,"Class":"2","Title":null,"ISSN":null,"Review":false,"Eidtions":null},{"Id":212897,"Class":"2","Title":null,"ISSN":null,"Review":false,"Eidtions":null},{"Id":212898,"Class":"2","Title":null,"ISSN":null,"Review":false,"Eidtions":null},{"Id":212901,"Class":"3","Title":null,"ISSN":null,"Review":false,"Eidtions":null},{"Id":212909,"Class":"2","Title":null,"ISSN":null,"Review":false,"Eidtions":null},{"Id":212946,"Class":"3","Title":null,"ISSN":null,"Review":false,"Eidtions":null},{"Id":212951,"Class":"3","Title":null,"ISSN":null,"Review":false,"Eidtions":null},{"Id":212966,"Class":"3","Title":null,"ISSN":null,"Review":false,"Eidtions":null},{"Id":212981,"Class":"3","Title":null,"ISSN":null,"Review":false,"Eidtions":null},{"Id":212991,"Class":"2","Title":null,"ISSN":null,"Review":false,"Eidtions":null},{"Id":213011,"Class":"4","Title":null,"ISSN":null,"Review":false,"Eidtions":null},{"Id":213064,"Class":"2","Title":null,"ISSN":null,"Review":false,"Eidtions":null},{"Id":213087,"Class":"3","Title":null,"ISSN":null,"Review":false,"Eidtions":null},{"Id":213111,"Class":"2","Title":null,"ISSN":null,"Review":false,"Eidtions":null},{"Id":213184,"Class":"2","Title":null,"ISSN":null,"Review":false,"Eidtions":null},{"Id":213266,"Class":"3","Title":null,"ISSN":null,"Review":false,"Eidtions":null},{"Id":213283,"Class":"3","Title":null,"ISSN":null,"Review":false,"Eidtions":null},{"Id":213285,"Class":"3","Title":null,"ISSN":null,"Review":false,"Eidtions":null},{"Id":213289,"Class":"2","Title":null,"ISSN":null,"Review":false,"Eidtions":null},{"Id":213326,"Class":"2","Title":null,"ISSN":null,"Review":false,"Eidtions":null},{"Id":213341,"Class":"3","Title":null,"ISSN":null,"Review":false,"Eidtions":null},{"Id":213351,"Class":"3","Title":null,"ISSN":null,"Review":false,"Eidtions":null},{"Id":213352,"Class":"4","Title":null,"ISSN":null,"Review":false,"Eidtions":null},{"Id":213354,"Class":"2","Title":null,"ISSN":null,"Review":false,"Eidtions":null},{"Id":213378,"Class":"3","Title":null,"ISSN":null,"Review":false,"Eidtions":null},{"Id":213401,"Class":"2","Title":null,"ISSN":null,"Review":false,"Eidtions":null},{"Id":213486,"Class":"2","Title":null,"ISSN":null,"Review":false,"Eidtions":null},{"Id":213513,"Class":"3","Title":null,"ISSN":null,"Review":false,"Eidtions":null},{"Id":213528,"Class":"2","Title":null,"ISSN":null,"Review":false,"Eidtions":null},{"Id":213556,"Class":"4","Title":null,"ISSN":null,"Review":false,"Eidtions":null},{"Id":213562,"Class":"3","Title":null,"ISSN":null,"Review":false,"Eidtions":null},{"Id":213567,"Class":"3","Title":null,"ISSN":null,"Review":false,"Eidtions":null},{"Id":213573,"Class":"3","Title":null,"ISSN":null,"Review":false,"Eidtions":null},{"Id":213586,"Class":"3","Title":null,"ISSN":null,"Review":false,"Eidtions":null},{"Id":213591,"Class":"3","Title":null,"ISSN":null,"Review":false,"Eidtions":null},{"Id":213619,"Class":"4","Title":null,"ISSN":null,"Review":false,"Eidtions":null},{"Id":213632,"Class":"3","Title":null,"ISSN":null,"Review":false,"Eidtions":null},{"Id":213656,"Class":"4","Title":null,"ISSN":null,"Review":false,"Eidtions":null},{"Id":213680,"Class":"2","Title":null,"ISSN":null,"Review":false,"Eidtions":null},{"Id":213690,"Class":"3","Title":null,"ISSN":null,"Review":false,"Eidtions":null},{"Id":213701,"Class":"2","Title":null,"ISSN":null,"Review":false,"Eidtions":null},{"Id":213705,"Class":"3","Title":null,"ISSN":null,"Review":false,"Eidtions":null},{"Id":213725,"Class":"2","Title":null,"ISSN":null,"Review":false,"Eidtions":null},{"Id":213786,"Class":"3","Title":null,"ISSN":null,"Review":false,"Eidtions":null},{"Id":213796,"Class":"3","Title":null,"ISSN":null,"Review":false,"Eidtions":null},{"Id":213799,"Class":"3","Title":null,"ISSN":null,"Review":false,"Eidtions":null},{"Id":213800,"Class":"4","Title":null,"ISSN":null,"Review":false,"Eidtions":null},{"Id":213804,"Class":"3","Title":null,"ISSN":null,"Review":false,"Eidtions":null},{"Id":213814,"Class":"3","Title":null,"ISSN":null,"Review":false,"Eidtions":null},{"Id":213821,"Class":"3","Title":null,"ISSN":null,"Review":false,"Eidtions":null},{"Id":213828,"Class":"3","Title":null,"ISSN":null,"Review":false,"Eidtions":null},{"Id":213871,"Class":"3","Title":null,"ISSN":null,"Review":false,"Eidtions":null},{"Id":213909,"Class":"3","Title":null,"ISSN":null,"Review":false,"Eidtions":null},{"Id":213924,"Class":"3","Title":null,"ISSN":null,"Review":false,"Eidtions":null},{"Id":213969,"Class":"4","Title":null,"ISSN":null,"Review":false,"Eidtions":null},{"Id":213970,"Class":"4","Title":null,"ISSN":null,"Review":false,"Eidtions":null},{"Id":213976,"Class":"2","Title":null,"ISSN":null,"Review":false,"Eidtions":null},{"Id":213992,"Class":"4","Title":null,"ISSN":null,"Review":false,"Eidtions":null},{"Id":214001,"Class":"4","Title":null,"ISSN":null,"Review":false,"Eidtions":null},{"Id":214024,"Class":"3","Title":null,"ISSN":null,"Review":false,"Eidtions":null},{"Id":214034,"Class":"3","Title":null,"ISSN":null,"Review":false,"Eidtions":null},{"Id":214070,"Class":"3","Title":null,"ISSN":null,"Review":false,"Eidtions":null},{"Id":214076,"Class":"2","Title":null,"ISSN":null,"Review":false,"Eidtions":null},{"Id":214086,"Class":"2","Title":null,"ISSN":null,"Review":false,"Eidtions":null},{"Id":214165,"Class":"3","Title":null,"ISSN":null,"Review":false,"Eidtions":null},{"Id":214183,"Class":"3","Title":null,"ISSN":null,"Review":false,"Eidtions":null},{"Id":214197,"Class":"4","Title":null,"ISSN":null,"Review":false,"Eidtions":null},{"Id":214265,"Class":"3","Title":null,"ISSN":null,"Review":false,"Eidtions":null},{"Id":214292,"Class":"4","Title":null,"ISSN":null,"Review":false,"Eidtions":null},{"Id":214294,"Class":"4","Title":null,"ISSN":null,"Review":false,"Eidtions":null},{"Id":214295,"Class":"2","Title":null,"ISSN":null,"Review":false,"Eidtions":null},{"Id":214334,"Class":"2","Title":null,"ISSN":null,"Review":false,"Eidtions":null},{"Id":214356,"Class":"2","Title":null,"ISSN":null,"Review":false,"Eidtions":null},{"Id":214431,"Class":"3","Title":null,"ISSN":null,"Review":false,"Eidtions":null},{"Id":214535,"Class":"3","Title":null,"ISSN":null,"Review":false,"Eidtions":null},{"Id":214619,"Class":"4","Title":null,"ISSN":null,"Review":false,"Eidtions":null},{"Id":214620,"Class":"3","Title":null,"ISSN":null,"Review":false,"Eidtions":null},{"Id":214656,"Class":"4","Title":null,"ISSN":null,"Review":false,"Eidtions":null},{"Id":214657,"Class":"3","Title":null,"ISSN":null,"Review":false,"Eidtions":null},{"Id":214707,"Class":"3","Title":null,"ISSN":null,"Review":false,"Eidtions":null},{"Id":214804,"Class":"3","Title":null,"ISSN":null,"Review":false,"Eidtions":null},{"Id":214828,"Class":"4","Title":null,"ISSN":null,"Review":false,"Eidtions":null},{"Id":214863,"Class":"2","Title":null,"ISSN":null,"Review":false,"Eidtions":null},{"Id":214902,"Class":"2","Title":null,"ISSN":null,"Review":false,"Eidtions":null},{"Id":214917,"Class":"3","Title":null,"ISSN":null,"Review":false,"Eidtions":null},{"Id":214941,"Class":"3","Title":null,"ISSN":null,"Review":false,"Eidtions":null},{"Id":214948,"Class":"3","Title":null,"ISSN":null,"Review":false,"Eidtions":null},{"Id":215074,"Class":"3","Title":null,"ISSN":null,"Review":false,"Eidtions":null},{"Id":215130,"Class":"4","Title":null,"ISSN":null,"Review":false,"Eidtions":null},{"Id":215147,"Class":"4","Title":null,"ISSN":null,"Review":false,"Eidtions":null},{"Id":215220,"Class":"3","Title":null,"ISSN":null,"Review":false,"Eidtions":null},{"Id":215221,"Class":"2","Title":null,"ISSN":null,"Review":false,"Eidtions":null},{"Id":215222,"Class":"4","Title":null,"ISSN":null,"Review":false,"Eidtions":null},{"Id":215265,"Class":"4","Title":null,"ISSN":null,"Review":false,"Eidtions":null},{"Id":215285,"Class":"3","Title":null,"ISSN":null,"Review":false,"Eidtions":null},{"Id":215295,"Class":"4","Title":null,"ISSN":null,"Review":false,"Eidtions":null},{"Id":215327,"Class":"4","Title":null,"ISSN":null,"Review":false,"Eidtions":null},{"Id":215362,"Class":"4","Title":null,"ISSN":null,"Review":false,"Eidtions":null},{"Id":215390,"Class":"2","Title":null,"ISSN":null,"Review":false,"Eidtions":null},{"Id":215438,"Class":"4","Title":null,"ISSN":null,"Review":false,"Eidtions":null},{"Id":215440,"Class":"2","Title":null,"ISSN":null,"Review":false,"Eidtions":null},{"Id":215453,"Class":"4","Title":null,"ISSN":null,"Review":false,"Eidtions":null},{"Id":215459,"Class":"4","Title":null,"ISSN":null,"Review":false,"Eidtions":null},{"Id":215497,"Class":"3","Title":null,"ISSN":null,"Review":false,"Eidtions":null},{"Id":215543,"Class":"3","Title":null,"ISSN":null,"Review":false,"Eidtions":null},{"Id":215576,"Class":"4","Title":null,"ISSN":null,"Review":false,"Eidtions":null},{"Id":215587,"Class":"3","Title":null,"ISSN":null,"Review":false,"Eidtions":null},{"Id":215659,"Class":"3","Title":null,"ISSN":null,"Review":false,"Eidtions":null},{"Id":215667,"Class":"3","Title":null,"ISSN":null,"Review":false,"Eidtions":null},{"Id":215680,"Class":"4","Title":null,"ISSN":null,"Review":false,"Eidtions":null},{"Id":215734,"Class":"4","Title":null,"ISSN":null,"Review":false,"Eidtions":null},{"Id":215780,"Class":"4","Title":null,"ISSN":null,"Review":false,"Eidtions":null},{"Id":215788,"Class":"3","Title":null,"ISSN":null,"Review":false,"Eidtions":null},{"Id":215799,"Class":"4","Title":null,"ISSN":null,"Review":false,"Eidtions":null},{"Id":215810,"Class":"4","Title":null,"ISSN":null,"Review":false,"Eidtions":null},{"Id":215814,"Class":"3","Title":null,"ISSN":null,"Review":false,"Eidtions":null},{"Id":215839,"Class":"4","Title":null,"ISSN":null,"Review":false,"Eidtions":null},{"Id":215865,"Class":"3","Title":null,"ISSN":null,"Review":false,"Eidtions":null},{"Id":215906,"Class":"4","Title":null,"ISSN":null,"Review":false,"Eidtions":null},{"Id":215924,"Class":"4","Title":null,"ISSN":null,"Review":false,"Eidtions":null},{"Id":215948,"Class":"3","Title":null,"ISSN":null,"Review":false,"Eidtions":null},{"Id":215962,"Class":"3","Title":null,"ISSN":null,"Review":false,"Eidtions":null},{"Id":215987,"Class":"3","Title":null,"ISSN":null,"Review":false,"Eidtions":null},{"Id":216037,"Class":"2","Title":null,"ISSN":null,"Review":false,"Eidtions":null},{"Id":216044,"Class":"3","Title":null,"ISSN":null,"Review":false,"Eidtions":null},{"Id":216051,"Class":"3","Title":null,"ISSN":null,"Review":false,"Eidtions":null},{"Id":216063,"Class":"4","Title":null,"ISSN":null,"Review":false,"Eidtions":null},{"Id":216082,"Class":"4","Title":null,"ISSN":null,"Review":false,"Eidtions":null},{"Id":216110,"Class":"4","Title":null,"ISSN":null,"Review":false,"Eidtions":null},{"Id":216122,"Class":"4","Title":null,"ISSN":null,"Review":false,"Eidtions":null},{"Id":216167,"Class":"4","Title":null,"ISSN":null,"Review":false,"Eidtions":null},{"Id":216176,"Class":"4","Title":null,"ISSN":null,"Review":false,"Eidtions":null},{"Id":216194,"Class":"3","Title":null,"ISSN":null,"Review":false,"Eidtions":null},{"Id":216198,"Class":"4","Title":null,"ISSN":null,"Review":false,"Eidtions":null},{"Id":216206,"Class":"4","Title":null,"ISSN":null,"Review":false,"Eidtions":null},{"Id":216219,"Class":"4","Title":null,"ISSN":null,"Review":false,"Eidtions":null},{"Id":216272,"Class":"4","Title":null,"ISSN":null,"Review":false,"Eidtions":null},{"Id":216304,"Class":"4","Title":null,"ISSN":null,"Review":false,"Eidtions":null},{"Id":216317,"Class":"3","Title":null,"ISSN":null,"Review":false,"Eidtions":null},{"Id":216335,"Class":"3","Title":null,"ISSN":null,"Review":false,"Eidtions":null},{"Id":216341,"Class":"3","Title":null,"ISSN":null,"Review":false,"Eidtions":null},{"Id":216406,"Class":"4","Title":null,"ISSN":null,"Review":false,"Eidtions":null},{"Id":216423,"Class":"4","Title":null,"ISSN":null,"Review":false,"Eidtions":null},{"Id":216445,"Class":"4","Title":null,"ISSN":null,"Review":false,"Eidtions":null},{"Id":216447,"Class":"4","Title":null,"ISSN":null,"Review":false,"Eidtions":null},{"Id":216473,"Class":"4","Title":null,"ISSN":null,"Review":false,"Eidtions":null},{"Id":216479,"Class":"4","Title":null,"ISSN":null,"Review":false,"Eidtions":null},{"Id":216482,"Class":"4","Title":null,"ISSN":null,"Review":false,"Eidtions":null},{"Id":216499,"Class":"4","Title":null,"ISSN":null,"Review":false,"Eidtions":null},{"Id":216559,"Class":"4","Title":null,"ISSN":null,"Review":false,"Eidtions":null},{"Id":216615,"Class":"4","Title":null,"ISSN":null,"Review":false,"Eidtions":null},{"Id":216644,"Class":"3","Title":null,"ISSN":null,"Review":false,"Eidtions":null},{"Id":216650,"Class":"2","Title":null,"ISSN":null,"Review":false,"Eidtions":null},{"Id":216677,"Class":"4","Title":null,"ISSN":null,"Review":false,"Eidtions":null},{"Id":216698,"Class":"3","Title":null,"ISSN":null,"Review":false,"Eidtions":null},{"Id":216706,"Class":"4","Title":null,"ISSN":null,"Review":false,"Eidtions":null},{"Id":216735,"Class":"4","Title":null,"ISSN":null,"Review":false,"Eidtions":null},{"Id":216754,"Class":"2","Title":null,"ISSN":null,"Review":false,"Eidtions":null},{"Id":216784,"Class":"4","Title":null,"ISSN":null,"Review":false,"Eidtions":null},{"Id":216785,"Class":"4","Title":null,"ISSN":null,"Review":false,"Eidtions":null},{"Id":216799,"Class":"4","Title":null,"ISSN":null,"Review":false,"Eidtions":null},{"Id":216800,"Class":"4","Title":null,"ISSN":null,"Review":false,"Eidtions":null},{"Id":216871,"Class":"4","Title":null,"ISSN":null,"Review":false,"Eidtions":null},{"Id":216881,"Class":"4","Title":null,"ISSN":null,"Review":false,"Eidtions":null},{"Id":216883,"Class":"4","Title":null,"ISSN":null,"Review":false,"Eidtions":null},{"Id":216963,"Class":"4","Title":null,"ISSN":null,"Review":false,"Eidtions":null},{"Id":216968,"Class":"4","Title":null,"ISSN":null,"Review":false,"Eidtions":null},{"Id":216978,"Class":"3","Title":null,"ISSN":null,"Review":false,"Eidtions":null},{"Id":216987,"Class":"4","Title":null,"ISSN":null,"Review":false,"Eidtions":null},{"Id":217002,"Class":"4","Title":null,"ISSN":null,"Review":false,"Eidtions":null},{"Id":217012,"Class":"4","Title":null,"ISSN":null,"Review":false,"Eidtions":null},{"Id":217013,"Class":"4","Title":null,"ISSN":null,"Review":false,"Eidtions":null},{"Id":217051,"Class":"4","Title":null,"ISSN":null,"Review":false,"Eidtions":null},{"Id":217054,"Class":"4","Title":null,"ISSN":null,"Review":false,"Eidtions":null},{"Id":217073,"Class":"3","Title":null,"ISSN":null,"Review":false,"Eidtions":null},{"Id":217108,"Class":"4","Title":null,"ISSN":null,"Review":false,"Eidtions":null},{"Id":217124,"Class":"4","Title":null,"ISSN":null,"Review":false,"Eidtions":null},{"Id":217143,"Class":"4","Title":null,"ISSN":null,"Review":false,"Eidtions":null},{"Id":217177,"Class":"4","Title":null,"ISSN":null,"Review":false,"Eidtions":null},{"Id":217178,"Class":"4","Title":null,"ISSN":null,"Review":false,"Eidtions":null},{"Id":217179,"Class":"4","Title":null,"ISSN":null,"Review":false,"Eidtions":null},{"Id":217199,"Class":"3","Title":null,"ISSN":null,"Review":false,"Eidtions":null},{"Id":217201,"Class":"4","Title":null,"ISSN":null,"Review":false,"Eidtions":null},{"Id":217203,"Class":"4","Title":null,"ISSN":null,"Review":false,"Eidtions":null},{"Id":217251,"Class":"3","Title":null,"ISSN":null,"Review":false,"Eidtions":null},{"Id":217302,"Class":"4","Title":null,"ISSN":null,"Review":false,"Eidtions":null},{"Id":217321,"Class":"2","Title":null,"ISSN":null,"Review":false,"Eidtions":null},{"Id":217324,"Class":"4","Title":null,"ISSN":null,"Review":false,"Eidtions":null},{"Id":217330,"Class":"4","Title":null,"ISSN":null,"Review":false,"Eidtions":null},{"Id":217345,"Class":"4","Title":null,"ISSN":null,"Review":false,"Eidtions":null},{"Id":217347,"Class":"4","Title":null,"ISSN":null,"Review":false,"Eidtions":null},{"Id":217354,"Class":"2","Title":null,"ISSN":null,"Review":false,"Eidtions":null},{"Id":217407,"Class":"4","Title":null,"ISSN":null,"Review":false,"Eidtions":null},{"Id":217410,"Class":"4","Title":null,"ISSN":null,"Review":false,"Eidtions":null},{"Id":217411,"Class":"3","Title":null,"ISSN":null,"Review":false,"Eidtions":null},{"Id":217416,"Class":"4","Title":null,"ISSN":null,"Review":false,"Eidtions":null},{"Id":217446,"Class":"4","Title":null,"ISSN":null,"Review":false,"Eidtions":null},{"Id":217465,"Class":"4","Title":null,"ISSN":null,"Review":false,"Eidtions":null},{"Id":217484,"Class":"4","Title":null,"ISSN":null,"Review":false,"Eidtions":null},{"Id":217494,"Class":"4","Title":null,"ISSN":null,"Review":false,"Eidtions":null},{"Id":217525,"Class":"3","Title":null,"ISSN":null,"Review":false,"Eidtions":null},{"Id":217540,"Class":"3","Title":null,"ISSN":null,"Review":false,"Eidtions":null},{"Id":217552,"Class":"4","Title":null,"ISSN":null,"Review":false,"Eidtions":null},{"Id":217558,"Class":"4","Title":null,"ISSN":null,"Review":false,"Eidtions":null},{"Id":217572,"Class":"4","Title":null,"ISSN":null,"Review":false,"Eidtions":null},{"Id":217625,"Class":"4","Title":null,"ISSN":null,"Review":false,"Eidtions":null},{"Id":217629,"Class":"4","Title":null,"ISSN":null,"Review":false,"Eidtions":null},{"Id":217637,"Class":"2","Title":null,"ISSN":null,"Review":false,"Eidtions":null},{"Id":217651,"Class":"4","Title":null,"ISSN":null,"Review":false,"Eidtions":null},{"Id":217678,"Class":"3","Title":null,"ISSN":null,"Review":false,"Eidtions":null},{"Id":217694,"Class":"3","Title":null,"ISSN":null,"Review":false,"Eidtions":null},{"Id":217696,"Class":"3","Title":null,"ISSN":null,"Review":false,"Eidtions":null},{"Id":217726,"Class":"4","Title":null,"ISSN":null,"Review":false,"Eidtions":null},{"Id":217775,"Class":"4","Title":null,"ISSN":null,"Review":false,"Eidtions":null},{"Id":217780,"Class":"4","Title":null,"ISSN":null,"Review":false,"Eidtions":null},{"Id":217792,"Class":"4","Title":null,"ISSN":null,"Review":false,"Eidtions":null},{"Id":217832,"Class":"3","Title":null,"ISSN":null,"Review":false,"Eidtions":null},{"Id":217840,"Class":"4","Title":null,"ISSN":null,"Review":false,"Eidtions":null},{"Id":217842,"Class":"4","Title":null,"ISSN":null,"Review":false,"Eidtions":null},{"Id":217856,"Class":"4","Title":null,"ISSN":null,"Review":false,"Eidtions":null},{"Id":217857,"Class":"4","Title":null,"ISSN":null,"Review":false,"Eidtions":null},{"Id":217957,"Class":"4","Title":null,"ISSN":null,"Review":false,"Eidtions":null},{"Id":217961,"Class":"4","Title":null,"ISSN":null,"Review":false,"Eidtions":null},{"Id":217988,"Class":"3","Title":null,"ISSN":null,"Review":false,"Eidtions":null},{"Id":217994,"Class":"4","Title":null,"ISSN":null,"Review":false,"Eidtions":null},{"Id":218010,"Class":"4","Title":null,"ISSN":null,"Review":false,"Eidtions":null},{"Id":218051,"Class":"3","Title":null,"ISSN":null,"Review":false,"Eidtions":null},{"Id":218063,"Class":"4","Title":null,"ISSN":null,"Review":false,"Eidtions":null},{"Id":218088,"Class":"4","Title":null,"ISSN":null,"Review":false,"Eidtions":null},{"Id":218119,"Class":"2","Title":null,"ISSN":null,"Review":false,"Eidtions":null},{"Id":218135,"Class":"4","Title":null,"ISSN":null,"Review":false,"Eidtions":null},{"Id":218137,"Class":"4","Title":null,"ISSN":null,"Review":false,"Eidtions":null},{"Id":218141,"Class":"4","Title":null,"ISSN":null,"Review":false,"Eidtions":null},{"Id":218148,"Class":"4","Title":null,"ISSN":null,"Review":false,"Eidtions":null},{"Id":218179,"Class":"3","Title":null,"ISSN":null,"Review":false,"Eidtions":null},{"Id":218188,"Class":"4","Title":null,"ISSN":null,"Review":false,"Eidtions":null},{"Id":218193,"Class":"4","Title":null,"ISSN":null,"Review":false,"Eidtions":null},{"Id":218235,"Class":"4","Title":null,"ISSN":null,"Review":false,"Eidtions":null},{"Id":218239,"Class":"4","Title":null,"ISSN":null,"Review":false,"Eidtions":null},{"Id":218242,"Class":"2","Title":null,"ISSN":null,"Review":false,"Eidtions":null},{"Id":218278,"Class":"4","Title":null,"ISSN":null,"Review":false,"Eidtions":null},{"Id":218281,"Class":"3","Title":null,"ISSN":null,"Review":false,"Eidtions":null},{"Id":218309,"Class":"4","Title":null,"ISSN":null,"Review":false,"Eidtions":null},{"Id":218311,"Class":"4","Title":null,"ISSN":null,"Review":false,"Eidtions":null},{"Id":218338,"Class":"4","Title":null,"ISSN":null,"Review":false,"Eidtions":null},{"Id":218356,"Class":"4","Title":null,"ISSN":null,"Review":false,"Eidtions":null},{"Id":218370,"Class":"4","Title":null,"ISSN":null,"Review":false,"Eidtions":null},{"Id":218430,"Class":"4","Title":null,"ISSN":null,"Review":false,"Eidtions":null},{"Id":218451,"Class":"4","Title":null,"ISSN":null,"Review":false,"Eidtions":null},{"Id":218462,"Class":"4","Title":null,"ISSN":null,"Review":false,"Eidtions":null},{"Id":218526,"Class":"4","Title":null,"ISSN":null,"Review":false,"Eidtions":null},{"Id":218579,"Class":"4","Title":null,"ISSN":null,"Review":false,"Eidtions":null},{"Id":218619,"Class":"4","Title":null,"ISSN":null,"Review":false,"Eidtions":null},{"Id":218664,"Class":"4","Title":null,"ISSN":null,"Review":false,"Eidtions":null},{"Id":218670,"Class":"3","Title":null,"ISSN":null,"Review":false,"Eidtions":null},{"Id":218684,"Class":"4","Title":null,"ISSN":null,"Review":false,"Eidtions":null},{"Id":218708,"Class":"4","Title":null,"ISSN":null,"Review":false,"Eidtions":null},{"Id":218731,"Class":"4","Title":null,"ISSN":null,"Review":false,"Eidtions":null},{"Id":218743,"Class":"4","Title":null,"ISSN":null,"Review":false,"Eidtions":null},{"Id":218749,"Class":"4","Title":null,"ISSN":null,"Review":false,"Eidtions":null},{"Id":218767,"Class":"4","Title":null,"ISSN":null,"Review":false,"Eidtions":null},{"Id":218772,"Class":"4","Title":null,"ISSN":null,"Review":false,"Eidtions":null},{"Id":218805,"Class":"4","Title":null,"ISSN":null,"Review":false,"Eidtions":null},{"Id":218814,"Class":"3","Title":null,"ISSN":null,"Review":false,"Eidtions":null},{"Id":218862,"Class":"4","Title":null,"ISSN":null,"Review":false,"Eidtions":null},{"Id":218866,"Class":"4","Title":null,"ISSN":null,"Review":false,"Eidtions":null},{"Id":218870,"Class":"4","Title":null,"ISSN":null,"Review":false,"Eidtions":null},{"Id":218883,"Class":"4","Title":null,"ISSN":null,"Review":false,"Eidtions":null},{"Id":218917,"Class":"3","Title":null,"ISSN":null,"Review":false,"Eidtions":null},{"Id":218959,"Class":"4","Title":null,"ISSN":null,"Review":false,"Eidtions":null},{"Id":218975,"Class":"4","Title":null,"ISSN":null,"Review":false,"Eidtions":null},{"Id":218986,"Class":"4","Title":null,"ISSN":null,"Review":false,"Eidtions":null},{"Id":219035,"Class":"4","Title":null,"ISSN":null,"Review":false,"Eidtions":null},{"Id":219042,"Class":"4","Title":null,"ISSN":null,"Review":false,"Eidtions":null},{"Id":219047,"Class":"3","Title":null,"ISSN":null,"Review":false,"Eidtions":null},{"Id":219068,"Class":"4","Title":null,"ISSN":null,"Review":false,"Eidtions":null},{"Id":219101,"Class":"4","Title":null,"ISSN":null,"Review":false,"Eidtions":null},{"Id":219125,"Class":"4","Title":null,"ISSN":null,"Review":false,"Eidtions":null},{"Id":219174,"Class":"4","Title":null,"ISSN":null,"Review":false,"Eidtions":null},{"Id":219187,"Class":"4","Title":null,"ISSN":null,"Review":false,"Eidtions":null},{"Id":219191,"Class":"4","Title":null,"ISSN":null,"Review":false,"Eidtions":null},{"Id":219199,"Class":"4","Title":null,"ISSN":null,"Review":false,"Eidtions":null},{"Id":219240,"Class":"4","Title":null,"ISSN":null,"Review":false,"Eidtions":null},{"Id":219261,"Class":"4","Title":null,"ISSN":null,"Review":false,"Eidtions":null},{"Id":219282,"Class":"4","Title":null,"ISSN":null,"Review":false,"Eidtions":null},{"Id":219284,"Class":"4","Title":null,"ISSN":null,"Review":false,"Eidtions":null},{"Id":219306,"Class":"4","Title":null,"ISSN":null,"Review":false,"Eidtions":null},{"Id":219317,"Class":"4","Title":null,"ISSN":null,"Review":false,"Eidtions":null},{"Id":219377,"Class":"4","Title":null,"ISSN":null,"Review":false,"Eidtions":null},{"Id":219417,"Class":"4","Title":null,"ISSN":null,"Review":false,"Eidtions":null},{"Id":219439,"Class":"4","Title":null,"ISSN":null,"Review":false,"Eidtions":null},{"Id":219461,"Class":"4","Title":null,"ISSN":null,"Review":false,"Eidtions":null},{"Id":219479,"Class":"4","Title":null,"ISSN":null,"Review":false,"Eidtions":null},{"Id":219538,"Class":"3","Title":null,"ISSN":null,"Review":false,"Eidtions":null},{"Id":219553,"Class":"4","Title":null,"ISSN":null,"Review":false,"Eidtions":null},{"Id":219562,"Class":"4","Title":null,"ISSN":null,"Review":false,"Eidtions":null},{"Id":219591,"Class":"4","Title":null,"ISSN":null,"Review":false,"Eidtions":null},{"Id":219603,"Class":"4","Title":null,"ISSN":null,"Review":false,"Eidtions":null},{"Id":219609,"Class":"4","Title":null,"ISSN":null,"Review":false,"Eidtions":null},{"Id":219612,"Class":"4","Title":null,"ISSN":null,"Review":false,"Eidtions":null},{"Id":219688,"Class":"4","Title":null,"ISSN":null,"Review":false,"Eidtions":null},{"Id":219696,"Class":"4","Title":null,"ISSN":null,"Review":false,"Eidtions":null},{"Id":219711,"Class":"3","Title":null,"ISSN":null,"Review":false,"Eidtions":null},{"Id":219737,"Class":"3","Title":null,"ISSN":null,"Review":false,"Eidtions":null},{"Id":219754,"Class":"4","Title":null,"ISSN":null,"Review":false,"Eidtions":null},{"Id":219755,"Class":"4","Title":null,"ISSN":null,"Review":false,"Eidtions":null},{"Id":219766,"Class":"4","Title":null,"ISSN":null,"Review":false,"Eidtions":null},{"Id":219774,"Class":"4","Title":null,"ISSN":null,"Review":false,"Eidtions":null},{"Id":219826,"Class":"3","Title":null,"ISSN":null,"Review":false,"Eidtions":null},{"Id":219838,"Class":"4","Title":null,"ISSN":null,"Review":false,"Eidtions":null},{"Id":219893,"Class":"4","Title":null,"ISSN":null,"Review":false,"Eidtions":null},{"Id":219894,"Class":"4","Title":null,"ISSN":null,"Review":false,"Eidtions":null},{"Id":219899,"Class":"4","Title":null,"ISSN":null,"Review":false,"Eidtions":null},{"Id":219905,"Class":"3","Title":null,"ISSN":null,"Review":false,"Eidtions":null},{"Id":220087,"Class":"4","Title":null,"ISSN":null,"Review":false,"Eidtions":null},{"Id":220088,"Class":"3","Title":null,"ISSN":null,"Review":false,"Eidtions":null},{"Id":220147,"Class":"4","Title":null,"ISSN":null,"Review":false,"Eidtions":null},{"Id":220185,"Class":"4","Title":null,"ISSN":null,"Review":false,"Eidtions":null},{"Id":220187,"Class":"4","Title":null,"ISSN":null,"Review":false,"Eidtions":null},{"Id":220199,"Class":"4","Title":null,"ISSN":null,"Review":false,"Eidtions":null},{"Id":220206,"Class":"3","Title":null,"ISSN":null,"Review":false,"Eidtions":null},{"Id":220218,"Class":"4","Title":null,"ISSN":null,"Review":false,"Eidtions":null},{"Id":220247,"Class":"3","Title":null,"ISSN":null,"Review":false,"Eidtions":null},{"Id":220256,"Class":"4","Title":null,"ISSN":null,"Review":false,"Eidtions":null},{"Id":220277,"Class":"4","Title":null,"ISSN":null,"Review":false,"Eidtions":null},{"Id":220281,"Class":"4","Title":null,"ISSN":null,"Review":false,"Eidtions":null},{"Id":220318,"Class":"4","Title":null,"ISSN":null,"Review":false,"Eidtions":null},{"Id":220355,"Class":"4","Title":null,"ISSN":null,"Review":false,"Eidtions":null},{"Id":220367,"Class":"4","Title":null,"ISSN":null,"Review":false,"Eidtions":null},{"Id":220374,"Class":"4","Title":null,"ISSN":null,"Review":false,"Eidtions":null},{"Id":220419,"Class":"4","Title":null,"ISSN":null,"Review":false,"Eidtions":null},{"Id":220427,"Class":"4","Title":null,"ISSN":null,"Review":false,"Eidtions":null},{"Id":220444,"Class":"4","Title":null,"ISSN":null,"Review":false,"Eidtions":null},{"Id":220460,"Class":"4","Title":null,"ISSN":null,"Review":false,"Eidtions":null},{"Id":220483,"Class":"4","Title":null,"ISSN":null,"Review":false,"Eidtions":null},{"Id":220489,"Class":"4","Title":null,"ISSN":null,"Review":false,"Eidtions":null},{"Id":220495,"Class":"4","Title":null,"ISSN":null,"Review":false,"Eidtions":null},{"Id":220496,"Class":"3","Title":null,"ISSN":null,"Review":false,"Eidtions":null},{"Id":220497,"Class":"4","Title":null,"ISSN":null,"Review":false,"Eidtions":null},{"Id":220538,"Class":"4","Title":null,"ISSN":null,"Review":false,"Eidtions":null},{"Id":220543,"Class":"3","Title":null,"ISSN":null,"Review":false,"Eidtions":null},{"Id":220561,"Class":"3","Title":null,"ISSN":null,"Review":false,"Eidtions":null},{"Id":220573,"Class":"4","Title":null,"ISSN":null,"Review":false,"Eidtions":null},{"Id":220576,"Class":"4","Title":null,"ISSN":null,"Review":false,"Eidtions":null},{"Id":220601,"Class":"4","Title":null,"ISSN":null,"Review":false,"Eidtions":null},{"Id":220621,"Class":"3","Title":null,"ISSN":null,"Review":false,"Eidtions":null},{"Id":220627,"Class":"3","Title":null,"ISSN":null,"Review":false,"Eidtions":null},{"Id":220658,"Class":"4","Title":null,"ISSN":null,"Review":false,"Eidtions":null},{"Id":220696,"Class":"4","Title":null,"ISSN":null,"Review":false,"Eidtions":null},{"Id":220712,"Class":"4","Title":null,"ISSN":null,"Review":false,"Eidtions":null},{"Id":220715,"Class":"4","Title":null,"ISSN":null,"Review":false,"Eidtions":null},{"Id":220727,"Class":"4","Title":null,"ISSN":null,"Review":false,"Eidtions":null},{"Id":220731,"Class":"3","Title":null,"ISSN":null,"Review":false,"Eidtions":null},{"Id":220765,"Class":"4","Title":null,"ISSN":null,"Review":false,"Eidtions":null},{"Id":220774,"Class":"4","Title":null,"ISSN":null,"Review":false,"Eidtions":null},{"Id":220850,"Class":"4","Title":null,"ISSN":null,"Review":false,"Eidtions":null},{"Id":220920,"Class":"4","Title":null,"ISSN":null,"Review":false,"Eidtions":null},{"Id":220924,"Class":"3","Title":null,"ISSN":null,"Review":false,"Eidtions":null},{"Id":220930,"Class":"4","Title":null,"ISSN":null,"Review":false,"Eidtions":null},{"Id":220938,"Class":"4","Title":null,"ISSN":null,"Review":false,"Eidtions":null},{"Id":221095,"Class":"4","Title":null,"ISSN":null,"Review":false,"Eidtions":null},{"Id":221128,"Class":"4","Title":null,"ISSN":null,"Review":false,"Eidtions":null},{"Id":221137,"Class":"4","Title":null,"ISSN":null,"Review":false,"Eidtions":null},{"Id":221198,"Class":"4","Title":null,"ISSN":null,"Review":false,"Eidtions":null},{"Id":221225,"Class":"4","Title":null,"ISSN":null,"Review":false,"Eidtions":null},{"Id":221277,"Class":"4","Title":null,"ISSN":null,"Review":false,"Eidtions":null},{"Id":221290,"Class":"4","Title":null,"ISSN":null,"Review":false,"Eidtions":null},{"Id":221291,"Class":"4","Title":null,"ISSN":null,"Review":false,"Eidtions":null},{"Id":221320,"Class":"4","Title":null,"ISSN":null,"Review":false,"Eidtions":null},{"Id":221329,"Class":"4","Title":null,"ISSN":null,"Review":false,"Eidtions":null},{"Id":221336,"Class":"4","Title":null,"ISSN":null,"Review":false,"Eidtions":null},{"Id":221339,"Class":"4","Title":null,"ISSN":null,"Review":false,"Eidtions":null},{"Id":221360,"Class":"4","Title":null,"ISSN":null,"Review":false,"Eidtions":null},{"Id":221385,"Class":"4","Title":null,"ISSN":null,"Review":false,"Eidtions":null},{"Id":221443,"Class":"4","Title":null,"ISSN":null,"Review":false,"Eidtions":null},{"Id":221468,"Class":"4","Title":null,"ISSN":null,"Review":false,"Eidtions":null},{"Id":221562,"Class":"4","Title":null,"ISSN":null,"Review":false,"Eidtions":null},{"Id":221586,"Class":"4","Title":null,"ISSN":null,"Review":false,"Eidtions":null},{"Id":221631,"Class":"4","Title":null,"ISSN":null,"Review":false,"Eidtions":null},{"Id":221723,"Class":"4","Title":null,"ISSN":null,"Review":false,"Eidtions":null},{"Id":221874,"Class":"4","Title":null,"ISSN":null,"Review":false,"Eidtions":null},{"Id":221947,"Class":"4","Title":null,"ISSN":null,"Review":false,"Eidtions":null},{"Id":221993,"Class":"4","Title":null,"ISSN":null,"Review":false,"Eidtions":null},{"Id":222114,"Class":"4","Title":null,"ISSN":null,"Review":false,"Eidtions":null},{"Id":222140,"Class":"4","Title":null,"ISSN":null,"Review":false,"Eidtions":null},{"Id":222220,"Class":"4","Title":null,"ISSN":null,"Review":false,"Eidtions":null},{"Id":222261,"Class":"4","Title":null,"ISSN":null,"Review":false,"Eidtions":null}]