[{"Id":176904,"Class":"1","Title":null,"ISSN":null,"Review":false,"Eidtions":null},{"Id":176905,"Class":"1","Title":null,"ISSN":null,"Review":false,"Eidtions":null},{"Id":176911,"Class":"1","Title":null,"ISSN":null,"Review":false,"Eidtions":null},{"Id":176913,"Class":"1","Title":null,"ISSN":null,"Review":false,"Eidtions":null},{"Id":176926,"Class":"1","Title":null,"ISSN":null,"Review":false,"Eidtions":null},{"Id":176932,"Class":"1","Title":null,"ISSN":null,"Review":false,"Eidtions":null},{"Id":176937,"Class":"1","Title":null,"ISSN":null,"Review":false,"Eidtions":null},{"Id":176954,"Class":"1","Title":null,"ISSN":null,"Review":false,"Eidtions":null},{"Id":176974,"Class":"1","Title":null,"ISSN":null,"Review":false,"Eidtions":null},{"Id":176983,"Class":"1","Title":null,"ISSN":null,"Review":false,"Eidtions":null},{"Id":176986,"Class":"1","Title":null,"ISSN":null,"Review":false,"Eidtions":null},{"Id":176993,"Class":"1","Title":null,"ISSN":null,"Review":false,"Eidtions":null},{"Id":176998,"Class":"1","Title":null,"ISSN":null,"Review":false,"Eidtions":null},{"Id":177010,"Class":"1","Title":null,"ISSN":null,"Review":false,"Eidtions":null},{"Id":177015,"Class":"1","Title":null,"ISSN":null,"Review":false,"Eidtions":null},{"Id":177016,"Class":"1","Title":null,"ISSN":null,"Review":false,"Eidtions":null},{"Id":177024,"Class":"2","Title":null,"ISSN":null,"Review":false,"Eidtions":null},{"Id":177027,"Class":"1","Title":null,"ISSN":null,"Review":false,"Eidtions":null},{"Id":177029,"Class":"1","Title":null,"ISSN":null,"Review":false,"Eidtions":null},{"Id":177039,"Class":"1","Title":null,"ISSN":null,"Review":false,"Eidtions":null},{"Id":177040,"Class":"1","Title":null,"ISSN":null,"Review":false,"Eidtions":null},{"Id":177049,"Class":"1","Title":null,"ISSN":null,"Review":false,"Eidtions":null},{"Id":177070,"Class":"1","Title":null,"ISSN":null,"Review":false,"Eidtions":null},{"Id":177071,"Class":"1","Title":null,"ISSN":null,"Review":false,"Eidtions":null},{"Id":177073,"Class":"1","Title":null,"ISSN":null,"Review":false,"Eidtions":null},{"Id":177079,"Class":"1","Title":null,"ISSN":null,"Review":false,"Eidtions":null},{"Id":177094,"Class":"1","Title":null,"ISSN":null,"Review":false,"Eidtions":null},{"Id":177097,"Class":"1","Title":null,"ISSN":null,"Review":false,"Eidtions":null},{"Id":177099,"Class":"1","Title":null,"ISSN":null,"Review":false,"Eidtions":null},{"Id":177100,"Class":"2","Title":null,"ISSN":null,"Review":false,"Eidtions":null},{"Id":177101,"Class":"2","Title":null,"ISSN":null,"Review":false,"Eidtions":null},{"Id":177103,"Class":"1","Title":null,"ISSN":null,"Review":false,"Eidtions":null},{"Id":177108,"Class":"1","Title":null,"ISSN":null,"Review":false,"Eidtions":null},{"Id":177112,"Class":"2","Title":null,"ISSN":null,"Review":false,"Eidtions":null},{"Id":177113,"Class":"1","Title":null,"ISSN":null,"Review":false,"Eidtions":null},{"Id":177115,"Class":"1","Title":null,"ISSN":null,"Review":false,"Eidtions":null},{"Id":177116,"Class":"1","Title":null,"ISSN":null,"Review":false,"Eidtions":null},{"Id":177128,"Class":"1","Title":null,"ISSN":null,"Review":false,"Eidtions":null},{"Id":177136,"Class":"1","Title":null,"ISSN":null,"Review":false,"Eidtions":null},{"Id":177143,"Class":"1","Title":null,"ISSN":null,"Review":false,"Eidtions":null},{"Id":177146,"Class":"1","Title":null,"ISSN":null,"Review":false,"Eidtions":null},{"Id":177147,"Class":"1","Title":null,"ISSN":null,"Review":false,"Eidtions":null},{"Id":177155,"Class":"1","Title":null,"ISSN":null,"Review":false,"Eidtions":null},{"Id":177157,"Class":"1","Title":null,"ISSN":null,"Review":false,"Eidtions":null},{"Id":177160,"Class":"1","Title":null,"ISSN":null,"Review":false,"Eidtions":null},{"Id":177185,"Class":"1","Title":null,"ISSN":null,"Review":false,"Eidtions":null},{"Id":177187,"Class":"1","Title":null,"ISSN":null,"Review":false,"Eidtions":null},{"Id":177188,"Class":"1","Title":null,"ISSN":null,"Review":false,"Eidtions":null},{"Id":177189,"Class":"1","Title":null,"ISSN":null,"Review":false,"Eidtions":null},{"Id":177190,"Class":"2","Title":null,"ISSN":null,"Review":false,"Eidtions":null},{"Id":177203,"Class":"1","Title":null,"ISSN":null,"Review":false,"Eidtions":null},{"Id":177207,"Class":"1","Title":null,"ISSN":null,"Review":false,"Eidtions":null},{"Id":177223,"Class":"1","Title":null,"ISSN":null,"Review":false,"Eidtions":null},{"Id":177224,"Class":"1","Title":null,"ISSN":null,"Review":false,"Eidtions":null},{"Id":177229,"Class":"2","Title":null,"ISSN":null,"Review":false,"Eidtions":null},{"Id":177241,"Class":"1","Title":null,"ISSN":null,"Review":false,"Eidtions":null},{"Id":177242,"Class":"1","Title":null,"ISSN":null,"Review":false,"Eidtions":null},{"Id":177255,"Class":"2","Title":null,"ISSN":null,"Review":false,"Eidtions":null},{"Id":177265,"Class":"1","Title":null,"ISSN":null,"Review":false,"Eidtions":null},{"Id":177276,"Class":"2","Title":null,"ISSN":null,"Review":false,"Eidtions":null},{"Id":177286,"Class":"1","Title":null,"ISSN":null,"Review":false,"Eidtions":null},{"Id":177289,"Class":"1","Title":null,"ISSN":null,"Review":false,"Eidtions":null},{"Id":177291,"Class":"1","Title":null,"ISSN":null,"Review":false,"Eidtions":null},{"Id":177311,"Class":"1","Title":null,"ISSN":null,"Review":false,"Eidtions":null},{"Id":177315,"Class":"1","Title":null,"ISSN":null,"Review":false,"Eidtions":null},{"Id":177319,"Class":"1","Title":null,"ISSN":null,"Review":false,"Eidtions":null},{"Id":177334,"Class":"1","Title":null,"ISSN":null,"Review":false,"Eidtions":null},{"Id":177340,"Class":"1","Title":null,"ISSN":null,"Review":false,"Eidtions":null},{"Id":177374,"Class":"2","Title":null,"ISSN":null,"Review":false,"Eidtions":null},{"Id":177375,"Class":"1","Title":null,"ISSN":null,"Review":false,"Eidtions":null},{"Id":177381,"Class":"2","Title":null,"ISSN":null,"Review":false,"Eidtions":null},{"Id":177382,"Class":"1","Title":null,"ISSN":null,"Review":false,"Eidtions":null},{"Id":177396,"Class":"2","Title":null,"ISSN":null,"Review":false,"Eidtions":null},{"Id":177407,"Class":"1","Title":null,"ISSN":null,"Review":false,"Eidtions":null},{"Id":177420,"Class":"1","Title":null,"ISSN":null,"Review":false,"Eidtions":null},{"Id":177421,"Class":"1","Title":null,"ISSN":null,"Review":false,"Eidtions":null},{"Id":177423,"Class":"2","Title":null,"ISSN":null,"Review":false,"Eidtions":null},{"Id":177438,"Class":"2","Title":null,"ISSN":null,"Review":false,"Eidtions":null},{"Id":177444,"Class":"1","Title":null,"ISSN":null,"Review":false,"Eidtions":null},{"Id":177445,"Class":"1","Title":null,"ISSN":null,"Review":false,"Eidtions":null},{"Id":177450,"Class":"1","Title":null,"ISSN":null,"Review":false,"Eidtions":null},{"Id":177456,"Class":"2","Title":null,"ISSN":null,"Review":false,"Eidtions":null},{"Id":177495,"Class":"1","Title":null,"ISSN":null,"Review":false,"Eidtions":null},{"Id":177499,"Class":"1","Title":null,"ISSN":null,"Review":false,"Eidtions":null},{"Id":177502,"Class":"2","Title":null,"ISSN":null,"Review":false,"Eidtions":null},{"Id":177536,"Class":"2","Title":null,"ISSN":null,"Review":false,"Eidtions":null},{"Id":177556,"Class":"2","Title":null,"ISSN":null,"Review":false,"Eidtions":null},{"Id":177578,"Class":"2","Title":null,"ISSN":null,"Review":false,"Eidtions":null},{"Id":177602,"Class":"1","Title":null,"ISSN":null,"Review":false,"Eidtions":null},{"Id":177609,"Class":"2","Title":null,"ISSN":null,"Review":false,"Eidtions":null},{"Id":177625,"Class":"2","Title":null,"ISSN":null,"Review":false,"Eidtions":null},{"Id":177632,"Class":"1","Title":null,"ISSN":null,"Review":false,"Eidtions":null},{"Id":177641,"Class":"2","Title":null,"ISSN":null,"Review":false,"Eidtions":null},{"Id":177654,"Class":"3","Title":null,"ISSN":null,"Review":false,"Eidtions":null},{"Id":177665,"Class":"2","Title":null,"ISSN":null,"Review":false,"Eidtions":null},{"Id":177681,"Class":"2","Title":null,"ISSN":null,"Review":false,"Eidtions":null},{"Id":177685,"Class":"2","Title":null,"ISSN":null,"Review":false,"Eidtions":null},{"Id":177711,"Class":"3","Title":null,"ISSN":null,"Review":false,"Eidtions":null},{"Id":177713,"Class":"2","Title":null,"ISSN":null,"Review":false,"Eidtions":null},{"Id":177737,"Class":"2","Title":null,"ISSN":null,"Review":false,"Eidtions":null},{"Id":177743,"Class":"2","Title":null,"ISSN":null,"Review":false,"Eidtions":null},{"Id":177752,"Class":"2","Title":null,"ISSN":null,"Review":false,"Eidtions":null},{"Id":177776,"Class":"2","Title":null,"ISSN":null,"Review":false,"Eidtions":null},{"Id":177779,"Class":"2","Title":null,"ISSN":null,"Review":false,"Eidtions":null},{"Id":177781,"Class":"3","Title":null,"ISSN":null,"Review":false,"Eidtions":null},{"Id":177800,"Class":"2","Title":null,"ISSN":null,"Review":false,"Eidtions":null},{"Id":177812,"Class":"2","Title":null,"ISSN":null,"Review":false,"Eidtions":null},{"Id":177830,"Class":"2","Title":null,"ISSN":null,"Review":false,"Eidtions":null},{"Id":177842,"Class":"3","Title":null,"ISSN":null,"Review":false,"Eidtions":null},{"Id":177843,"Class":"1","Title":null,"ISSN":null,"Review":false,"Eidtions":null},{"Id":177855,"Class":"2","Title":null,"ISSN":null,"Review":false,"Eidtions":null},{"Id":177885,"Class":"3","Title":null,"ISSN":null,"Review":false,"Eidtions":null},{"Id":177892,"Class":"2","Title":null,"ISSN":null,"Review":false,"Eidtions":null},{"Id":177915,"Class":"3","Title":null,"ISSN":null,"Review":false,"Eidtions":null},{"Id":177921,"Class":"2","Title":null,"ISSN":null,"Review":false,"Eidtions":null},{"Id":177926,"Class":"2","Title":null,"ISSN":null,"Review":false,"Eidtions":null},{"Id":177932,"Class":"2","Title":null,"ISSN":null,"Review":false,"Eidtions":null},{"Id":177952,"Class":"3","Title":null,"ISSN":null,"Review":false,"Eidtions":null},{"Id":177971,"Class":"2","Title":null,"ISSN":null,"Review":false,"Eidtions":null},{"Id":177974,"Class":"2","Title":null,"ISSN":null,"Review":false,"Eidtions":null},{"Id":177976,"Class":"3","Title":null,"ISSN":null,"Review":false,"Eidtions":null},{"Id":177980,"Class":"2","Title":null,"ISSN":null,"Review":false,"Eidtions":null},{"Id":177992,"Class":"2","Title":null,"ISSN":null,"Review":false,"Eidtions":null},{"Id":177998,"Class":"3","Title":null,"ISSN":null,"Review":false,"Eidtions":null},{"Id":178002,"Class":"2","Title":null,"ISSN":null,"Review":false,"Eidtions":null},{"Id":178013,"Class":"2","Title":null,"ISSN":null,"Review":false,"Eidtions":null},{"Id":178027,"Class":"2","Title":null,"ISSN":null,"Review":false,"Eidtions":null},{"Id":178047,"Class":"2","Title":null,"ISSN":null,"Review":false,"Eidtions":null},{"Id":178049,"Class":"3","Title":null,"ISSN":null,"Review":false,"Eidtions":null},{"Id":178053,"Class":"2","Title":null,"ISSN":null,"Review":false,"Eidtions":null},{"Id":178070,"Class":"2","Title":null,"ISSN":null,"Review":false,"Eidtions":null},{"Id":178083,"Class":"3","Title":null,"ISSN":null,"Review":false,"Eidtions":null},{"Id":178085,"Class":"2","Title":null,"ISSN":null,"Review":false,"Eidtions":null},{"Id":178115,"Class":"2","Title":null,"ISSN":null,"Review":false,"Eidtions":null},{"Id":178136,"Class":"2","Title":null,"ISSN":null,"Review":false,"Eidtions":null},{"Id":178137,"Class":"2","Title":null,"ISSN":null,"Review":false,"Eidtions":null},{"Id":178163,"Class":"2","Title":null,"ISSN":null,"Review":false,"Eidtions":null},{"Id":178168,"Class":"3","Title":null,"ISSN":null,"Review":false,"Eidtions":null},{"Id":178183,"Class":"2","Title":null,"ISSN":null,"Review":false,"Eidtions":null},{"Id":178206,"Class":"1","Title":null,"ISSN":null,"Review":false,"Eidtions":null},{"Id":178207,"Class":"3","Title":null,"ISSN":null,"Review":false,"Eidtions":null},{"Id":178209,"Class":"2","Title":null,"ISSN":null,"Review":false,"Eidtions":null},{"Id":178220,"Class":"2","Title":null,"ISSN":null,"Review":false,"Eidtions":null},{"Id":178230,"Class":"2","Title":null,"ISSN":null,"Review":false,"Eidtions":null},{"Id":178232,"Class":"2","Title":null,"ISSN":null,"Review":false,"Eidtions":null},{"Id":178244,"Class":"2","Title":null,"ISSN":null,"Review":false,"Eidtions":null},{"Id":178248,"Class":"2","Title":null,"ISSN":null,"Review":false,"Eidtions":null},{"Id":178249,"Class":"2","Title":null,"ISSN":null,"Review":false,"Eidtions":null},{"Id":178267,"Class":"3","Title":null,"ISSN":null,"Review":false,"Eidtions":null},{"Id":178284,"Class":"3","Title":null,"ISSN":null,"Review":false,"Eidtions":null},{"Id":178289,"Class":"2","Title":null,"ISSN":null,"Review":false,"Eidtions":null},{"Id":178292,"Class":"3","Title":null,"ISSN":null,"Review":false,"Eidtions":null},{"Id":178293,"Class":"3","Title":null,"ISSN":null,"Review":false,"Eidtions":null},{"Id":178302,"Class":"2","Title":null,"ISSN":null,"Review":false,"Eidtions":null},{"Id":178308,"Class":"3","Title":null,"ISSN":null,"Review":false,"Eidtions":null},{"Id":178343,"Class":"2","Title":null,"ISSN":null,"Review":false,"Eidtions":null},{"Id":178355,"Class":"2","Title":null,"ISSN":null,"Review":false,"Eidtions":null},{"Id":178356,"Class":"2","Title":null,"ISSN":null,"Review":false,"Eidtions":null},{"Id":178363,"Class":"2","Title":null,"ISSN":null,"Review":false,"Eidtions":null},{"Id":178368,"Class":"4","Title":null,"ISSN":null,"Review":false,"Eidtions":null},{"Id":178384,"Class":"2","Title":null,"ISSN":null,"Review":false,"Eidtions":null},{"Id":178388,"Class":"2","Title":null,"ISSN":null,"Review":false,"Eidtions":null},{"Id":178389,"Class":"2","Title":null,"ISSN":null,"Review":false,"Eidtions":null},{"Id":178393,"Class":"3","Title":null,"ISSN":null,"Review":false,"Eidtions":null},{"Id":178404,"Class":"2","Title":null,"ISSN":null,"Review":false,"Eidtions":null},{"Id":178405,"Class":"1","Title":null,"ISSN":null,"Review":false,"Eidtions":null},{"Id":178422,"Class":"2","Title":null,"ISSN":null,"Review":false,"Eidtions":null},{"Id":178440,"Class":"2","Title":null,"ISSN":null,"Review":false,"Eidtions":null},{"Id":178445,"Class":"1","Title":null,"ISSN":null,"Review":false,"Eidtions":null},{"Id":178476,"Class":"2","Title":null,"ISSN":null,"Review":false,"Eidtions":null},{"Id":178480,"Class":"3","Title":null,"ISSN":null,"Review":false,"Eidtions":null},{"Id":178491,"Class":"3","Title":null,"ISSN":null,"Review":false,"Eidtions":null},{"Id":178493,"Class":"2","Title":null,"ISSN":null,"Review":false,"Eidtions":null},{"Id":178496,"Class":"2","Title":null,"ISSN":null,"Review":false,"Eidtions":null},{"Id":178520,"Class":"2","Title":null,"ISSN":null,"Review":false,"Eidtions":null},{"Id":178534,"Class":"2","Title":null,"ISSN":null,"Review":false,"Eidtions":null},{"Id":178548,"Class":"3","Title":null,"ISSN":null,"Review":false,"Eidtions":null},{"Id":178594,"Class":"1","Title":null,"ISSN":null,"Review":false,"Eidtions":null},{"Id":178595,"Class":"2","Title":null,"ISSN":null,"Review":false,"Eidtions":null},{"Id":178620,"Class":"2","Title":null,"ISSN":null,"Review":false,"Eidtions":null},{"Id":178623,"Class":"3","Title":null,"ISSN":null,"Review":false,"Eidtions":null},{"Id":178625,"Class":"2","Title":null,"ISSN":null,"Review":false,"Eidtions":null},{"Id":178628,"Class":"2","Title":null,"ISSN":null,"Review":false,"Eidtions":null},{"Id":178630,"Class":"3","Title":null,"ISSN":null,"Review":false,"Eidtions":null},{"Id":178634,"Class":"3","Title":null,"ISSN":null,"Review":false,"Eidtions":null},{"Id":178637,"Class":"2","Title":null,"ISSN":null,"Review":false,"Eidtions":null},{"Id":178660,"Class":"3","Title":null,"ISSN":null,"Review":false,"Eidtions":null},{"Id":178661,"Class":"3","Title":null,"ISSN":null,"Review":false,"Eidtions":null},{"Id":178671,"Class":"2","Title":null,"ISSN":null,"Review":false,"Eidtions":null},{"Id":178686,"Class":"3","Title":null,"ISSN":null,"Review":false,"Eidtions":null},{"Id":178698,"Class":"2","Title":null,"ISSN":null,"Review":false,"Eidtions":null},{"Id":178699,"Class":"2","Title":null,"ISSN":null,"Review":false,"Eidtions":null},{"Id":178705,"Class":"2","Title":null,"ISSN":null,"Review":false,"Eidtions":null},{"Id":178715,"Class":"2","Title":null,"ISSN":null,"Review":false,"Eidtions":null},{"Id":178716,"Class":"2","Title":null,"ISSN":null,"Review":false,"Eidtions":null},{"Id":178727,"Class":"3","Title":null,"ISSN":null,"Review":false,"Eidtions":null},{"Id":178740,"Class":"3","Title":null,"ISSN":null,"Review":false,"Eidtions":null},{"Id":178748,"Class":"2","Title":null,"ISSN":null,"Review":false,"Eidtions":null},{"Id":178750,"Class":"2","Title":null,"ISSN":null,"Review":false,"Eidtions":null},{"Id":178757,"Class":"2","Title":null,"ISSN":null,"Review":false,"Eidtions":null},{"Id":178759,"Class":"2","Title":null,"ISSN":null,"Review":false,"Eidtions":null},{"Id":178760,"Class":"2","Title":null,"ISSN":null,"Review":false,"Eidtions":null},{"Id":178769,"Class":"2","Title":null,"ISSN":null,"Review":false,"Eidtions":null},{"Id":178784,"Class":"2","Title":null,"ISSN":null,"Review":false,"Eidtions":null},{"Id":178787,"Class":"4","Title":null,"ISSN":null,"Review":false,"Eidtions":null},{"Id":178802,"Class":"2","Title":null,"ISSN":null,"Review":false,"Eidtions":null},{"Id":178808,"Class":"2","Title":null,"ISSN":null,"Review":false,"Eidtions":null},{"Id":178809,"Class":"2","Title":null,"ISSN":null,"Review":false,"Eidtions":null},{"Id":178822,"Class":"3","Title":null,"ISSN":null,"Review":false,"Eidtions":null},{"Id":178841,"Class":"1","Title":null,"ISSN":null,"Review":false,"Eidtions":null},{"Id":178855,"Class":"2","Title":null,"ISSN":null,"Review":false,"Eidtions":null},{"Id":178861,"Class":"4","Title":null,"ISSN":null,"Review":false,"Eidtions":null},{"Id":178864,"Class":"2","Title":null,"ISSN":null,"Review":false,"Eidtions":null},{"Id":178869,"Class":"3","Title":null,"ISSN":null,"Review":false,"Eidtions":null},{"Id":178878,"Class":"2","Title":null,"ISSN":null,"Review":false,"Eidtions":null},{"Id":178888,"Class":"2","Title":null,"ISSN":null,"Review":false,"Eidtions":null},{"Id":178904,"Class":"2","Title":null,"ISSN":null,"Review":false,"Eidtions":null},{"Id":178911,"Class":"4","Title":null,"ISSN":null,"Review":false,"Eidtions":null},{"Id":178912,"Class":"3","Title":null,"ISSN":null,"Review":false,"Eidtions":null},{"Id":178919,"Class":"3","Title":null,"ISSN":null,"Review":false,"Eidtions":null},{"Id":178932,"Class":"2","Title":null,"ISSN":null,"Review":false,"Eidtions":null},{"Id":178937,"Class":"3","Title":null,"ISSN":null,"Review":false,"Eidtions":null},{"Id":178956,"Class":"2","Title":null,"ISSN":null,"Review":false,"Eidtions":null},{"Id":178957,"Class":"3","Title":null,"ISSN":null,"Review":false,"Eidtions":null},{"Id":178959,"Class":"3","Title":null,"ISSN":null,"Review":false,"Eidtions":null},{"Id":178976,"Class":"2","Title":null,"ISSN":null,"Review":false,"Eidtions":null},{"Id":179006,"Class":"3","Title":null,"ISSN":null,"Review":false,"Eidtions":null},{"Id":179020,"Class":"2","Title":null,"ISSN":null,"Review":false,"Eidtions":null},{"Id":179025,"Class":"3","Title":null,"ISSN":null,"Review":false,"Eidtions":null},{"Id":179027,"Class":"3","Title":null,"ISSN":null,"Review":false,"Eidtions":null},{"Id":179045,"Class":"3","Title":null,"ISSN":null,"Review":false,"Eidtions":null},{"Id":179076,"Class":"2","Title":null,"ISSN":null,"Review":false,"Eidtions":null},{"Id":179079,"Class":"2","Title":null,"ISSN":null,"Review":false,"Eidtions":null},{"Id":179100,"Class":"3","Title":null,"ISSN":null,"Review":false,"Eidtions":null},{"Id":179122,"Class":"2","Title":null,"ISSN":null,"Review":false,"Eidtions":null},{"Id":179126,"Class":"3","Title":null,"ISSN":null,"Review":false,"Eidtions":null},{"Id":179135,"Class":"3","Title":null,"ISSN":null,"Review":false,"Eidtions":null},{"Id":179139,"Class":"3","Title":null,"ISSN":null,"Review":false,"Eidtions":null},{"Id":179145,"Class":"3","Title":null,"ISSN":null,"Review":false,"Eidtions":null},{"Id":179173,"Class":"2","Title":null,"ISSN":null,"Review":false,"Eidtions":null},{"Id":179176,"Class":"3","Title":null,"ISSN":null,"Review":false,"Eidtions":null},{"Id":179188,"Class":"2","Title":null,"ISSN":null,"Review":false,"Eidtions":null},{"Id":179201,"Class":"2","Title":null,"ISSN":null,"Review":false,"Eidtions":null},{"Id":179204,"Class":"3","Title":null,"ISSN":null,"Review":false,"Eidtions":null},{"Id":179214,"Class":"4","Title":null,"ISSN":null,"Review":false,"Eidtions":null},{"Id":179226,"Class":"3","Title":null,"ISSN":null,"Review":false,"Eidtions":null},{"Id":179235,"Class":"2","Title":null,"ISSN":null,"Review":false,"Eidtions":null},{"Id":179274,"Class":"3","Title":null,"ISSN":null,"Review":false,"Eidtions":null},{"Id":179287,"Class":"3","Title":null,"ISSN":null,"Review":false,"Eidtions":null},{"Id":179288,"Class":"3","Title":null,"ISSN":null,"Review":false,"Eidtions":null},{"Id":179309,"Class":"3","Title":null,"ISSN":null,"Review":false,"Eidtions":null},{"Id":179317,"Class":"3","Title":null,"ISSN":null,"Review":false,"Eidtions":null},{"Id":179323,"Class":"2","Title":null,"ISSN":null,"Review":false,"Eidtions":null},{"Id":179372,"Class":"2","Title":null,"ISSN":null,"Review":false,"Eidtions":null},{"Id":179391,"Class":"2","Title":null,"ISSN":null,"Review":false,"Eidtions":null},{"Id":179405,"Class":"4","Title":null,"ISSN":null,"Review":false,"Eidtions":null},{"Id":179432,"Class":"3","Title":null,"ISSN":null,"Review":false,"Eidtions":null},{"Id":179443,"Class":"4","Title":null,"ISSN":null,"Review":false,"Eidtions":null},{"Id":179456,"Class":"2","Title":null,"ISSN":null,"Review":false,"Eidtions":null},{"Id":179466,"Class":"2","Title":null,"ISSN":null,"Review":false,"Eidtions":null},{"Id":179471,"Class":"2","Title":null,"ISSN":null,"Review":false,"Eidtions":null},{"Id":179484,"Class":"3","Title":null,"ISSN":null,"Review":false,"Eidtions":null},{"Id":179492,"Class":"2","Title":null,"ISSN":null,"Review":false,"Eidtions":null},{"Id":179501,"Class":"2","Title":null,"ISSN":null,"Review":false,"Eidtions":null},{"Id":179508,"Class":"3","Title":null,"ISSN":null,"Review":false,"Eidtions":null},{"Id":179515,"Class":"4","Title":null,"ISSN":null,"Review":false,"Eidtions":null},{"Id":179521,"Class":"3","Title":null,"ISSN":null,"Review":false,"Eidtions":null},{"Id":179540,"Class":"2","Title":null,"ISSN":null,"Review":false,"Eidtions":null},{"Id":179558,"Class":"3","Title":null,"ISSN":null,"Review":false,"Eidtions":null},{"Id":179565,"Class":"2","Title":null,"ISSN":null,"Review":false,"Eidtions":null},{"Id":179566,"Class":"3","Title":null,"ISSN":null,"Review":false,"Eidtions":null},{"Id":179575,"Class":"3","Title":null,"ISSN":null,"Review":false,"Eidtions":null},{"Id":179585,"Class":"2","Title":null,"ISSN":null,"Review":false,"Eidtions":null},{"Id":179623,"Class":"3","Title":null,"ISSN":null,"Review":false,"Eidtions":null},{"Id":179626,"Class":"3","Title":null,"ISSN":null,"Review":false,"Eidtions":null},{"Id":179637,"Class":"2","Title":null,"ISSN":null,"Review":false,"Eidtions":null},{"Id":179646,"Class":"4","Title":null,"ISSN":null,"Review":false,"Eidtions":null},{"Id":179652,"Class":"3","Title":null,"ISSN":null,"Review":false,"Eidtions":null},{"Id":179672,"Class":"3","Title":null,"ISSN":null,"Review":false,"Eidtions":null},{"Id":179673,"Class":"2","Title":null,"ISSN":null,"Review":false,"Eidtions":null},{"Id":179701,"Class":"2","Title":null,"ISSN":null,"Review":false,"Eidtions":null},{"Id":179707,"Class":"4","Title":null,"ISSN":null,"Review":false,"Eidtions":null},{"Id":179715,"Class":"4","Title":null,"ISSN":null,"Review":false,"Eidtions":null},{"Id":179720,"Class":"3","Title":null,"ISSN":null,"Review":false,"Eidtions":null},{"Id":179727,"Class":"2","Title":null,"ISSN":null,"Review":false,"Eidtions":null},{"Id":179740,"Class":"3","Title":null,"ISSN":null,"Review":false,"Eidtions":null},{"Id":179766,"Class":"3","Title":null,"ISSN":null,"Review":false,"Eidtions":null},{"Id":179767,"Class":"3","Title":null,"ISSN":null,"Review":false,"Eidtions":null},{"Id":179774,"Class":"2","Title":null,"ISSN":null,"Review":false,"Eidtions":null},{"Id":179790,"Class":"4","Title":null,"ISSN":null,"Review":false,"Eidtions":null},{"Id":179805,"Class":"4","Title":null,"ISSN":null,"Review":false,"Eidtions":null},{"Id":179813,"Class":"2","Title":null,"ISSN":null,"Review":false,"Eidtions":null},{"Id":179823,"Class":"2","Title":null,"ISSN":null,"Review":false,"Eidtions":null},{"Id":179824,"Class":"3","Title":null,"ISSN":null,"Review":false,"Eidtions":null},{"Id":179858,"Class":"3","Title":null,"ISSN":null,"Review":false,"Eidtions":null},{"Id":179862,"Class":"3","Title":null,"ISSN":null,"Review":false,"Eidtions":null},{"Id":179870,"Class":"3","Title":null,"ISSN":null,"Review":false,"Eidtions":null},{"Id":179879,"Class":"3","Title":null,"ISSN":null,"Review":false,"Eidtions":null},{"Id":179885,"Class":"2","Title":null,"ISSN":null,"Review":false,"Eidtions":null},{"Id":179910,"Class":"3","Title":null,"ISSN":null,"Review":false,"Eidtions":null},{"Id":179912,"Class":"2","Title":null,"ISSN":null,"Review":false,"Eidtions":null},{"Id":179913,"Class":"3","Title":null,"ISSN":null,"Review":false,"Eidtions":null},{"Id":179924,"Class":"3","Title":null,"ISSN":null,"Review":false,"Eidtions":null},{"Id":179936,"Class":"2","Title":null,"ISSN":null,"Review":false,"Eidtions":null},{"Id":179960,"Class":"2","Title":null,"ISSN":null,"Review":false,"Eidtions":null},{"Id":179976,"Class":"3","Title":null,"ISSN":null,"Review":false,"Eidtions":null},{"Id":179977,"Class":"3","Title":null,"ISSN":null,"Review":false,"Eidtions":null},{"Id":179986,"Class":"3","Title":null,"ISSN":null,"Review":false,"Eidtions":null},{"Id":179988,"Class":"3","Title":null,"ISSN":null,"Review":false,"Eidtions":null},{"Id":180008,"Class":"2","Title":null,"ISSN":null,"Review":false,"Eidtions":null},{"Id":180013,"Class":"2","Title":null,"ISSN":null,"Review":false,"Eidtions":null},{"Id":180079,"Class":"3","Title":null,"ISSN":null,"Review":false,"Eidtions":null},{"Id":180128,"Class":"3","Title":null,"ISSN":null,"Review":false,"Eidtions":null},{"Id":180146,"Class":"4","Title":null,"ISSN":null,"Review":false,"Eidtions":null},{"Id":180151,"Class":"3","Title":null,"ISSN":null,"Review":false,"Eidtions":null},{"Id":180165,"Class":"3","Title":null,"ISSN":null,"Review":false,"Eidtions":null},{"Id":180194,"Class":"3","Title":null,"ISSN":null,"Review":false,"Eidtions":null},{"Id":180196,"Class":"2","Title":null,"ISSN":null,"Review":false,"Eidtions":null},{"Id":180219,"Class":"3","Title":null,"ISSN":null,"Review":false,"Eidtions":null},{"Id":180221,"Class":"3","Title":null,"ISSN":null,"Review":false,"Eidtions":null},{"Id":180224,"Class":"3","Title":null,"ISSN":null,"Review":false,"Eidtions":null},{"Id":180229,"Class":"2","Title":null,"ISSN":null,"Review":false,"Eidtions":null},{"Id":180258,"Class":"3","Title":null,"ISSN":null,"Review":false,"Eidtions":null},{"Id":180274,"Class":"2","Title":null,"ISSN":null,"Review":false,"Eidtions":null},{"Id":180275,"Class":"4","Title":null,"ISSN":null,"Review":false,"Eidtions":null},{"Id":180298,"Class":"4","Title":null,"ISSN":null,"Review":false,"Eidtions":null},{"Id":180315,"Class":"2","Title":null,"ISSN":null,"Review":false,"Eidtions":null},{"Id":180330,"Class":"3","Title":null,"ISSN":null,"Review":false,"Eidtions":null},{"Id":180349,"Class":"3","Title":null,"ISSN":null,"Review":false,"Eidtions":null},{"Id":180355,"Class":"4","Title":null,"ISSN":null,"Review":false,"Eidtions":null},{"Id":180357,"Class":"3","Title":null,"ISSN":null,"Review":false,"Eidtions":null},{"Id":180366,"Class":"3","Title":null,"ISSN":null,"Review":false,"Eidtions":null},{"Id":180373,"Class":"3","Title":null,"ISSN":null,"Review":false,"Eidtions":null},{"Id":180376,"Class":"3","Title":null,"ISSN":null,"Review":false,"Eidtions":null},{"Id":180382,"Class":"3","Title":null,"ISSN":null,"Review":false,"Eidtions":null},{"Id":180388,"Class":"3","Title":null,"ISSN":null,"Review":false,"Eidtions":null},{"Id":180405,"Class":"2","Title":null,"ISSN":null,"Review":false,"Eidtions":null},{"Id":180430,"Class":"3","Title":null,"ISSN":null,"Review":false,"Eidtions":null},{"Id":180431,"Class":"3","Title":null,"ISSN":null,"Review":false,"Eidtions":null},{"Id":180433,"Class":"2","Title":null,"ISSN":null,"Review":false,"Eidtions":null},{"Id":180436,"Class":"2","Title":null,"ISSN":null,"Review":false,"Eidtions":null},{"Id":180490,"Class":"3","Title":null,"ISSN":null,"Review":false,"Eidtions":null},{"Id":180502,"Class":"3","Title":null,"ISSN":null,"Review":false,"Eidtions":null},{"Id":180505,"Class":"3","Title":null,"ISSN":null,"Review":false,"Eidtions":null},{"Id":180507,"Class":"3","Title":null,"ISSN":null,"Review":false,"Eidtions":null},{"Id":180517,"Class":"3","Title":null,"ISSN":null,"Review":false,"Eidtions":null},{"Id":180554,"Class":"4","Title":null,"ISSN":null,"Review":false,"Eidtions":null},{"Id":180558,"Class":"3","Title":null,"ISSN":null,"Review":false,"Eidtions":null},{"Id":180571,"Class":"2","Title":null,"ISSN":null,"Review":false,"Eidtions":null},{"Id":180573,"Class":"3","Title":null,"ISSN":null,"Review":false,"Eidtions":null},{"Id":180586,"Class":"3","Title":null,"ISSN":null,"Review":false,"Eidtions":null},{"Id":180587,"Class":"4","Title":null,"ISSN":null,"Review":false,"Eidtions":null},{"Id":180588,"Class":"4","Title":null,"ISSN":null,"Review":false,"Eidtions":null},{"Id":180593,"Class":"2","Title":null,"ISSN":null,"Review":false,"Eidtions":null},{"Id":180612,"Class":"4","Title":null,"ISSN":null,"Review":false,"Eidtions":null},{"Id":180613,"Class":"3","Title":null,"ISSN":null,"Review":false,"Eidtions":null},{"Id":180619,"Class":"3","Title":null,"ISSN":null,"Review":false,"Eidtions":null},{"Id":180622,"Class":"3","Title":null,"ISSN":null,"Review":false,"Eidtions":null},{"Id":180638,"Class":"4","Title":null,"ISSN":null,"Review":false,"Eidtions":null},{"Id":180641,"Class":"3","Title":null,"ISSN":null,"Review":false,"Eidtions":null},{"Id":180648,"Class":"4","Title":null,"ISSN":null,"Review":false,"Eidtions":null},{"Id":180658,"Class":"3","Title":null,"ISSN":null,"Review":false,"Eidtions":null},{"Id":180661,"Class":"4","Title":null,"ISSN":null,"Review":false,"Eidtions":null},{"Id":180664,"Class":"4","Title":null,"ISSN":null,"Review":false,"Eidtions":null},{"Id":180693,"Class":"2","Title":null,"ISSN":null,"Review":false,"Eidtions":null},{"Id":180714,"Class":"3","Title":null,"ISSN":null,"Review":false,"Eidtions":null},{"Id":180740,"Class":"3","Title":null,"ISSN":null,"Review":false,"Eidtions":null},{"Id":180741,"Class":"3","Title":null,"ISSN":null,"Review":false,"Eidtions":null},{"Id":180776,"Class":"4","Title":null,"ISSN":null,"Review":false,"Eidtions":null},{"Id":180785,"Class":"4","Title":null,"ISSN":null,"Review":false,"Eidtions":null},{"Id":180828,"Class":"2","Title":null,"ISSN":null,"Review":false,"Eidtions":null},{"Id":180836,"Class":"3","Title":null,"ISSN":null,"Review":false,"Eidtions":null},{"Id":180851,"Class":"3","Title":null,"ISSN":null,"Review":false,"Eidtions":null},{"Id":180861,"Class":"4","Title":null,"ISSN":null,"Review":false,"Eidtions":null},{"Id":180873,"Class":"2","Title":null,"ISSN":null,"Review":false,"Eidtions":null},{"Id":180909,"Class":"3","Title":null,"ISSN":null,"Review":false,"Eidtions":null},{"Id":180913,"Class":"2","Title":null,"ISSN":null,"Review":false,"Eidtions":null},{"Id":180941,"Class":"3","Title":null,"ISSN":null,"Review":false,"Eidtions":null},{"Id":180971,"Class":"4","Title":null,"ISSN":null,"Review":false,"Eidtions":null},{"Id":180974,"Class":"3","Title":null,"ISSN":null,"Review":false,"Eidtions":null},{"Id":180975,"Class":"3","Title":null,"ISSN":null,"Review":false,"Eidtions":null},{"Id":180988,"Class":"3","Title":null,"ISSN":null,"Review":false,"Eidtions":null},{"Id":180989,"Class":"3","Title":null,"ISSN":null,"Review":false,"Eidtions":null},{"Id":180992,"Class":"3","Title":null,"ISSN":null,"Review":false,"Eidtions":null},{"Id":180999,"Class":"3","Title":null,"ISSN":null,"Review":false,"Eidtions":null},{"Id":181019,"Class":"3","Title":null,"ISSN":null,"Review":false,"Eidtions":null},{"Id":181033,"Class":"4","Title":null,"ISSN":null,"Review":false,"Eidtions":null},{"Id":181043,"Class":"4","Title":null,"ISSN":null,"Review":false,"Eidtions":null},{"Id":181050,"Class":"3","Title":null,"ISSN":null,"Review":false,"Eidtions":null},{"Id":181057,"Class":"3","Title":null,"ISSN":null,"Review":false,"Eidtions":null},{"Id":181067,"Class":"4","Title":null,"ISSN":null,"Review":false,"Eidtions":null},{"Id":181082,"Class":"3","Title":null,"ISSN":null,"Review":false,"Eidtions":null},{"Id":181090,"Class":"3","Title":null,"ISSN":null,"Review":false,"Eidtions":null},{"Id":181094,"Class":"4","Title":null,"ISSN":null,"Review":false,"Eidtions":null},{"Id":181108,"Class":"3","Title":null,"ISSN":null,"Review":false,"Eidtions":null},{"Id":181109,"Class":"4","Title":null,"ISSN":null,"Review":false,"Eidtions":null},{"Id":181114,"Class":"3","Title":null,"ISSN":null,"Review":false,"Eidtions":null},{"Id":181140,"Class":"3","Title":null,"ISSN":null,"Review":false,"Eidtions":null},{"Id":181147,"Class":"2","Title":null,"ISSN":null,"Review":false,"Eidtions":null},{"Id":181154,"Class":"4","Title":null,"ISSN":null,"Review":false,"Eidtions":null},{"Id":181188,"Class":"3","Title":null,"ISSN":null,"Review":false,"Eidtions":null},{"Id":181194,"Class":"4","Title":null,"ISSN":null,"Review":false,"Eidtions":null},{"Id":181217,"Class":"2","Title":null,"ISSN":null,"Review":false,"Eidtions":null},{"Id":181229,"Class":"3","Title":null,"ISSN":null,"Review":false,"Eidtions":null},{"Id":181249,"Class":"3","Title":null,"ISSN":null,"Review":false,"Eidtions":null},{"Id":181263,"Class":"2","Title":null,"ISSN":null,"Review":false,"Eidtions":null},{"Id":181304,"Class":"4","Title":null,"ISSN":null,"Review":false,"Eidtions":null},{"Id":181327,"Class":"3","Title":null,"ISSN":null,"Review":false,"Eidtions":null},{"Id":181361,"Class":"2","Title":null,"ISSN":null,"Review":false,"Eidtions":null},{"Id":181365,"Class":"4","Title":null,"ISSN":null,"Review":false,"Eidtions":null},{"Id":181405,"Class":"4","Title":null,"ISSN":null,"Review":false,"Eidtions":null},{"Id":181414,"Class":"3","Title":null,"ISSN":null,"Review":false,"Eidtions":null},{"Id":181425,"Class":"3","Title":null,"ISSN":null,"Review":false,"Eidtions":null},{"Id":181437,"Class":"2","Title":null,"ISSN":null,"Review":false,"Eidtions":null},{"Id":181444,"Class":"3","Title":null,"ISSN":null,"Review":false,"Eidtions":null},{"Id":181445,"Class":"4","Title":null,"ISSN":null,"Review":false,"Eidtions":null},{"Id":181455,"Class":"4","Title":null,"ISSN":null,"Review":false,"Eidtions":null},{"Id":181474,"Class":"4","Title":null,"ISSN":null,"Review":false,"Eidtions":null},{"Id":181479,"Class":"4","Title":null,"ISSN":null,"Review":false,"Eidtions":null},{"Id":181495,"Class":"3","Title":null,"ISSN":null,"Review":false,"Eidtions":null},{"Id":181501,"Class":"4","Title":null,"ISSN":null,"Review":false,"Eidtions":null},{"Id":181505,"Class":"4","Title":null,"ISSN":null,"Review":false,"Eidtions":null},{"Id":181509,"Class":"4","Title":null,"ISSN":null,"Review":false,"Eidtions":null},{"Id":181531,"Class":"3","Title":null,"ISSN":null,"Review":false,"Eidtions":null},{"Id":181549,"Class":"4","Title":null,"ISSN":null,"Review":false,"Eidtions":null},{"Id":181551,"Class":"4","Title":null,"ISSN":null,"Review":false,"Eidtions":null},{"Id":181566,"Class":"3","Title":null,"ISSN":null,"Review":false,"Eidtions":null},{"Id":181581,"Class":"3","Title":null,"ISSN":null,"Review":false,"Eidtions":null},{"Id":181584,"Class":"3","Title":null,"ISSN":null,"Review":false,"Eidtions":null},{"Id":181587,"Class":"4","Title":null,"ISSN":null,"Review":false,"Eidtions":null},{"Id":181588,"Class":"3","Title":null,"ISSN":null,"Review":false,"Eidtions":null},{"Id":181589,"Class":"3","Title":null,"ISSN":null,"Review":false,"Eidtions":null},{"Id":181595,"Class":"1","Title":null,"ISSN":null,"Review":false,"Eidtions":null},{"Id":181597,"Class":"2","Title":null,"ISSN":null,"Review":false,"Eidtions":null},{"Id":181609,"Class":"3","Title":null,"ISSN":null,"Review":false,"Eidtions":null},{"Id":181615,"Class":"3","Title":null,"ISSN":null,"Review":false,"Eidtions":null},{"Id":181619,"Class":"4","Title":null,"ISSN":null,"Review":false,"Eidtions":null},{"Id":181620,"Class":"4","Title":null,"ISSN":null,"Review":false,"Eidtions":null},{"Id":181633,"Class":"4","Title":null,"ISSN":null,"Review":false,"Eidtions":null},{"Id":181642,"Class":"3","Title":null,"ISSN":null,"Review":false,"Eidtions":null},{"Id":181656,"Class":"4","Title":null,"ISSN":null,"Review":false,"Eidtions":null},{"Id":181671,"Class":"4","Title":null,"ISSN":null,"Review":false,"Eidtions":null},{"Id":181677,"Class":"3","Title":null,"ISSN":null,"Review":false,"Eidtions":null},{"Id":181684,"Class":"3","Title":null,"ISSN":null,"Review":false,"Eidtions":null},{"Id":181733,"Class":"3","Title":null,"ISSN":null,"Review":false,"Eidtions":null},{"Id":181734,"Class":"4","Title":null,"ISSN":null,"Review":false,"Eidtions":null},{"Id":181740,"Class":"4","Title":null,"ISSN":null,"Review":false,"Eidtions":null},{"Id":181751,"Class":"3","Title":null,"ISSN":null,"Review":false,"Eidtions":null},{"Id":181773,"Class":"1","Title":null,"ISSN":null,"Review":false,"Eidtions":null},{"Id":181782,"Class":"3","Title":null,"ISSN":null,"Review":false,"Eidtions":null},{"Id":181787,"Class":"3","Title":null,"ISSN":null,"Review":false,"Eidtions":null},{"Id":181800,"Class":"4","Title":null,"ISSN":null,"Review":false,"Eidtions":null},{"Id":181834,"Class":"4","Title":null,"ISSN":null,"Review":false,"Eidtions":null},{"Id":181839,"Class":"4","Title":null,"ISSN":null,"Review":false,"Eidtions":null},{"Id":181840,"Class":"3","Title":null,"ISSN":null,"Review":false,"Eidtions":null},{"Id":181926,"Class":"3","Title":null,"ISSN":null,"Review":false,"Eidtions":null},{"Id":181938,"Class":"4","Title":null,"ISSN":null,"Review":false,"Eidtions":null},{"Id":181950,"Class":"3","Title":null,"ISSN":null,"Review":false,"Eidtions":null},{"Id":181956,"Class":"4","Title":null,"ISSN":null,"Review":false,"Eidtions":null},{"Id":181958,"Class":"3","Title":null,"ISSN":null,"Review":false,"Eidtions":null},{"Id":181983,"Class":"3","Title":null,"ISSN":null,"Review":false,"Eidtions":null},{"Id":181998,"Class":"4","Title":null,"ISSN":null,"Review":false,"Eidtions":null},{"Id":181999,"Class":"3","Title":null,"ISSN":null,"Review":false,"Eidtions":null},{"Id":182002,"Class":"2","Title":null,"ISSN":null,"Review":false,"Eidtions":null},{"Id":182004,"Class":"3","Title":null,"ISSN":null,"Review":false,"Eidtions":null},{"Id":182047,"Class":"4","Title":null,"ISSN":null,"Review":false,"Eidtions":null},{"Id":182057,"Class":"3","Title":null,"ISSN":null,"Review":false,"Eidtions":null},{"Id":182061,"Class":"4","Title":null,"ISSN":null,"Review":false,"Eidtions":null},{"Id":182092,"Class":"3","Title":null,"ISSN":null,"Review":false,"Eidtions":null},{"Id":182094,"Class":"4","Title":null,"ISSN":null,"Review":false,"Eidtions":null},{"Id":182097,"Class":"4","Title":null,"ISSN":null,"Review":false,"Eidtions":null},{"Id":182109,"Class":"4","Title":null,"ISSN":null,"Review":false,"Eidtions":null},{"Id":182112,"Class":"4","Title":null,"ISSN":null,"Review":false,"Eidtions":null},{"Id":182161,"Class":"3","Title":null,"ISSN":null,"Review":false,"Eidtions":null},{"Id":182195,"Class":"3","Title":null,"ISSN":null,"Review":false,"Eidtions":null},{"Id":182204,"Class":"4","Title":null,"ISSN":null,"Review":false,"Eidtions":null},{"Id":182230,"Class":"4","Title":null,"ISSN":null,"Review":false,"Eidtions":null},{"Id":182232,"Class":"3","Title":null,"ISSN":null,"Review":false,"Eidtions":null},{"Id":182235,"Class":"4","Title":null,"ISSN":null,"Review":false,"Eidtions":null},{"Id":182240,"Class":"4","Title":null,"ISSN":null,"Review":false,"Eidtions":null},{"Id":182280,"Class":"4","Title":null,"ISSN":null,"Review":false,"Eidtions":null},{"Id":182282,"Class":"3","Title":null,"ISSN":null,"Review":false,"Eidtions":null},{"Id":182323,"Class":"4","Title":null,"ISSN":null,"Review":false,"Eidtions":null},{"Id":182328,"Class":"4","Title":null,"ISSN":null,"Review":false,"Eidtions":null},{"Id":182354,"Class":"3","Title":null,"ISSN":null,"Review":false,"Eidtions":null},{"Id":182358,"Class":"3","Title":null,"ISSN":null,"Review":false,"Eidtions":null},{"Id":182374,"Class":"2","Title":null,"ISSN":null,"Review":false,"Eidtions":null},{"Id":182396,"Class":"3","Title":null,"ISSN":null,"Review":false,"Eidtions":null},{"Id":182410,"Class":"4","Title":null,"ISSN":null,"Review":false,"Eidtions":null},{"Id":182411,"Class":"3","Title":null,"ISSN":null,"Review":false,"Eidtions":null},{"Id":182460,"Class":"3","Title":null,"ISSN":null,"Review":false,"Eidtions":null},{"Id":182464,"Class":"4","Title":null,"ISSN":null,"Review":false,"Eidtions":null},{"Id":182483,"Class":"4","Title":null,"ISSN":null,"Review":false,"Eidtions":null},{"Id":182495,"Class":"4","Title":null,"ISSN":null,"Review":false,"Eidtions":null},{"Id":182536,"Class":"4","Title":null,"ISSN":null,"Review":false,"Eidtions":null},{"Id":182544,"Class":"3","Title":null,"ISSN":null,"Review":false,"Eidtions":null},{"Id":182552,"Class":"4","Title":null,"ISSN":null,"Review":false,"Eidtions":null},{"Id":182558,"Class":"4","Title":null,"ISSN":null,"Review":false,"Eidtions":null},{"Id":182596,"Class":"4","Title":null,"ISSN":null,"Review":false,"Eidtions":null},{"Id":182602,"Class":"4","Title":null,"ISSN":null,"Review":false,"Eidtions":null},{"Id":182620,"Class":"4","Title":null,"ISSN":null,"Review":false,"Eidtions":null},{"Id":182628,"Class":"4","Title":null,"ISSN":null,"Review":false,"Eidtions":null},{"Id":182668,"Class":"4","Title":null,"ISSN":null,"Review":false,"Eidtions":null},{"Id":182674,"Class":"3","Title":null,"ISSN":null,"Review":false,"Eidtions":null},{"Id":182683,"Class":"3","Title":null,"ISSN":null,"Review":false,"Eidtions":null},{"Id":182687,"Class":"4","Title":null,"ISSN":null,"Review":false,"Eidtions":null},{"Id":182743,"Class":"4","Title":null,"ISSN":null,"Review":false,"Eidtions":null},{"Id":182774,"Class":"3","Title":null,"ISSN":null,"Review":false,"Eidtions":null},{"Id":182788,"Class":"4","Title":null,"ISSN":null,"Review":false,"Eidtions":null},{"Id":182790,"Class":"4","Title":null,"ISSN":null,"Review":false,"Eidtions":null},{"Id":182807,"Class":"4","Title":null,"ISSN":null,"Review":false,"Eidtions":null},{"Id":182811,"Class":"4","Title":null,"ISSN":null,"Review":false,"Eidtions":null},{"Id":182857,"Class":"3","Title":null,"ISSN":null,"Review":false,"Eidtions":null},{"Id":182866,"Class":"4","Title":null,"ISSN":null,"Review":false,"Eidtions":null},{"Id":182870,"Class":"4","Title":null,"ISSN":null,"Review":false,"Eidtions":null},{"Id":182878,"Class":"4","Title":null,"ISSN":null,"Review":false,"Eidtions":null},{"Id":182892,"Class":"4","Title":null,"ISSN":null,"Review":false,"Eidtions":null},{"Id":182943,"Class":"4","Title":null,"ISSN":null,"Review":false,"Eidtions":null},{"Id":182960,"Class":"4","Title":null,"ISSN":null,"Review":false,"Eidtions":null},{"Id":182990,"Class":"4","Title":null,"ISSN":null,"Review":false,"Eidtions":null},{"Id":183018,"Class":"3","Title":null,"ISSN":null,"Review":false,"Eidtions":null},{"Id":183036,"Class":"4","Title":null,"ISSN":null,"Review":false,"Eidtions":null},{"Id":183082,"Class":"4","Title":null,"ISSN":null,"Review":false,"Eidtions":null},{"Id":183122,"Class":"4","Title":null,"ISSN":null,"Review":false,"Eidtions":null},{"Id":183127,"Class":"4","Title":null,"ISSN":null,"Review":false,"Eidtions":null},{"Id":183132,"Class":"4","Title":null,"ISSN":null,"Review":false,"Eidtions":null},{"Id":183134,"Class":"3","Title":null,"ISSN":null,"Review":false,"Eidtions":null},{"Id":183136,"Class":"4","Title":null,"ISSN":null,"Review":false,"Eidtions":null},{"Id":183155,"Class":"4","Title":null,"ISSN":null,"Review":false,"Eidtions":null},{"Id":183159,"Class":"3","Title":null,"ISSN":null,"Review":false,"Eidtions":null},{"Id":183190,"Class":"4","Title":null,"ISSN":null,"Review":false,"Eidtions":null},{"Id":183196,"Class":"4","Title":null,"ISSN":null,"Review":false,"Eidtions":null},{"Id":183209,"Class":"4","Title":null,"ISSN":null,"Review":false,"Eidtions":null},{"Id":183244,"Class":"4","Title":null,"ISSN":null,"Review":false,"Eidtions":null},{"Id":183264,"Class":"4","Title":null,"ISSN":null,"Review":false,"Eidtions":null},{"Id":183270,"Class":"3","Title":null,"ISSN":null,"Review":false,"Eidtions":null},{"Id":183287,"Class":"4","Title":null,"ISSN":null,"Review":false,"Eidtions":null},{"Id":183289,"Class":"4","Title":null,"ISSN":null,"Review":false,"Eidtions":null},{"Id":183293,"Class":"4","Title":null,"ISSN":null,"Review":false,"Eidtions":null},{"Id":183296,"Class":"4","Title":null,"ISSN":null,"Review":false,"Eidtions":null},{"Id":183331,"Class":"3","Title":null,"ISSN":null,"Review":false,"Eidtions":null},{"Id":183346,"Class":"4","Title":null,"ISSN":null,"Review":false,"Eidtions":null},{"Id":183358,"Class":"4","Title":null,"ISSN":null,"Review":false,"Eidtions":null},{"Id":183391,"Class":"3","Title":null,"ISSN":null,"Review":false,"Eidtions":null},{"Id":183445,"Class":"2","Title":null,"ISSN":null,"Review":false,"Eidtions":null},{"Id":183453,"Class":"4","Title":null,"ISSN":null,"Review":false,"Eidtions":null},{"Id":183463,"Class":"4","Title":null,"ISSN":null,"Review":false,"Eidtions":null},{"Id":183465,"Class":"4","Title":null,"ISSN":null,"Review":false,"Eidtions":null},{"Id":183480,"Class":"4","Title":null,"ISSN":null,"Review":false,"Eidtions":null},{"Id":183485,"Class":"3","Title":null,"ISSN":null,"Review":false,"Eidtions":null},{"Id":183500,"Class":"4","Title":null,"ISSN":null,"Review":false,"Eidtions":null},{"Id":183508,"Class":"4","Title":null,"ISSN":null,"Review":false,"Eidtions":null},{"Id":183522,"Class":"4","Title":null,"ISSN":null,"Review":false,"Eidtions":null},{"Id":183530,"Class":"4","Title":null,"ISSN":null,"Review":false,"Eidtions":null},{"Id":183557,"Class":"3","Title":null,"ISSN":null,"Review":false,"Eidtions":null},{"Id":183560,"Class":"3","Title":null,"ISSN":null,"Review":false,"Eidtions":null},{"Id":183620,"Class":"3","Title":null,"ISSN":null,"Review":false,"Eidtions":null},{"Id":183639,"Class":"4","Title":null,"ISSN":null,"Review":false,"Eidtions":null},{"Id":183648,"Class":"4","Title":null,"ISSN":null,"Review":false,"Eidtions":null},{"Id":183659,"Class":"4","Title":null,"ISSN":null,"Review":false,"Eidtions":null},{"Id":183665,"Class":"4","Title":null,"ISSN":null,"Review":false,"Eidtions":null},{"Id":183720,"Class":"3","Title":null,"ISSN":null,"Review":false,"Eidtions":null},{"Id":183750,"Class":"3","Title":null,"ISSN":null,"Review":false,"Eidtions":null},{"Id":183792,"Class":"4","Title":null,"ISSN":null,"Review":false,"Eidtions":null},{"Id":183814,"Class":"4","Title":null,"ISSN":null,"Review":false,"Eidtions":null},{"Id":183830,"Class":"3","Title":null,"ISSN":null,"Review":false,"Eidtions":null},{"Id":183842,"Class":"3","Title":null,"ISSN":null,"Review":false,"Eidtions":null},{"Id":183860,"Class":"4","Title":null,"ISSN":null,"Review":false,"Eidtions":null},{"Id":183913,"Class":"3","Title":null,"ISSN":null,"Review":false,"Eidtions":null},{"Id":183929,"Class":"4","Title":null,"ISSN":null,"Review":false,"Eidtions":null},{"Id":183952,"Class":"3","Title":null,"ISSN":null,"Review":false,"Eidtions":null},{"Id":183959,"Class":"4","Title":null,"ISSN":null,"Review":false,"Eidtions":null},{"Id":183960,"Class":"3","Title":null,"ISSN":null,"Review":false,"Eidtions":null},{"Id":183962,"Class":"3","Title":null,"ISSN":null,"Review":false,"Eidtions":null},{"Id":184054,"Class":"4","Title":null,"ISSN":null,"Review":false,"Eidtions":null},{"Id":184110,"Class":"3","Title":null,"ISSN":null,"Review":false,"Eidtions":null},{"Id":184114,"Class":"4","Title":null,"ISSN":null,"Review":false,"Eidtions":null},{"Id":184137,"Class":"4","Title":null,"ISSN":null,"Review":false,"Eidtions":null},{"Id":184141,"Class":"3","Title":null,"ISSN":null,"Review":false,"Eidtions":null},{"Id":184143,"Class":"4","Title":null,"ISSN":null,"Review":false,"Eidtions":null},{"Id":184205,"Class":"4","Title":null,"ISSN":null,"Review":false,"Eidtions":null},{"Id":184207,"Class":"4","Title":null,"ISSN":null,"Review":false,"Eidtions":null},{"Id":184211,"Class":"4","Title":null,"ISSN":null,"Review":false,"Eidtions":null},{"Id":184212,"Class":"3","Title":null,"ISSN":null,"Review":false,"Eidtions":null},{"Id":184239,"Class":"4","Title":null,"ISSN":null,"Review":false,"Eidtions":null},{"Id":184253,"Class":"4","Title":null,"ISSN":null,"Review":false,"Eidtions":null},{"Id":184277,"Class":"3","Title":null,"ISSN":null,"Review":false,"Eidtions":null},{"Id":184282,"Class":"4","Title":null,"ISSN":null,"Review":false,"Eidtions":null},{"Id":184297,"Class":"4","Title":null,"ISSN":null,"Review":false,"Eidtions":null},{"Id":184301,"Class":"4","Title":null,"ISSN":null,"Review":false,"Eidtions":null},{"Id":184303,"Class":"4","Title":null,"ISSN":null,"Review":false,"Eidtions":null},{"Id":184312,"Class":"4","Title":null,"ISSN":null,"Review":false,"Eidtions":null},{"Id":184325,"Class":"4","Title":null,"ISSN":null,"Review":false,"Eidtions":null},{"Id":184336,"Class":"4","Title":null,"ISSN":null,"Review":false,"Eidtions":null},{"Id":184345,"Class":"3","Title":null,"ISSN":null,"Review":false,"Eidtions":null},{"Id":184376,"Class":"4","Title":null,"ISSN":null,"Review":false,"Eidtions":null},{"Id":184395,"Class":"4","Title":null,"ISSN":null,"Review":false,"Eidtions":null},{"Id":184406,"Class":"4","Title":null,"ISSN":null,"Review":false,"Eidtions":null},{"Id":184410,"Class":"3","Title":null,"ISSN":null,"Review":false,"Eidtions":null},{"Id":184415,"Class":"4","Title":null,"ISSN":null,"Review":false,"Eidtions":null},{"Id":184435,"Class":"4","Title":null,"ISSN":null,"Review":false,"Eidtions":null},{"Id":184461,"Class":"4","Title":null,"ISSN":null,"Review":false,"Eidtions":null},{"Id":184498,"Class":"4","Title":null,"ISSN":null,"Review":false,"Eidtions":null},{"Id":184499,"Class":"4","Title":null,"ISSN":null,"Review":false,"Eidtions":null},{"Id":184527,"Class":"4","Title":null,"ISSN":null,"Review":false,"Eidtions":null},{"Id":184538,"Class":"4","Title":null,"ISSN":null,"Review":false,"Eidtions":null},{"Id":184580,"Class":"3","Title":null,"ISSN":null,"Review":false,"Eidtions":null},{"Id":184618,"Class":"3","Title":null,"ISSN":null,"Review":false,"Eidtions":null},{"Id":184624,"Class":"4","Title":null,"ISSN":null,"Review":false,"Eidtions":null},{"Id":184639,"Class":"4","Title":null,"ISSN":null,"Review":false,"Eidtions":null},{"Id":184657,"Class":"4","Title":null,"ISSN":null,"Review":false,"Eidtions":null},{"Id":184672,"Class":"3","Title":null,"ISSN":null,"Review":false,"Eidtions":null},{"Id":184689,"Class":"4","Title":null,"ISSN":null,"Review":false,"Eidtions":null},{"Id":184711,"Class":"4","Title":null,"ISSN":null,"Review":false,"Eidtions":null},{"Id":184743,"Class":"4","Title":null,"ISSN":null,"Review":false,"Eidtions":null},{"Id":184748,"Class":"4","Title":null,"ISSN":null,"Review":false,"Eidtions":null},{"Id":184759,"Class":"4","Title":null,"ISSN":null,"Review":false,"Eidtions":null},{"Id":184797,"Class":"4","Title":null,"ISSN":null,"Review":false,"Eidtions":null},{"Id":184814,"Class":"3","Title":null,"ISSN":null,"Review":false,"Eidtions":null},{"Id":184827,"Class":"4","Title":null,"ISSN":null,"Review":false,"Eidtions":null},{"Id":184839,"Class":"3","Title":null,"ISSN":null,"Review":false,"Eidtions":null},{"Id":184855,"Class":"4","Title":null,"ISSN":null,"Review":false,"Eidtions":null},{"Id":184878,"Class":"4","Title":null,"ISSN":null,"Review":false,"Eidtions":null},{"Id":184892,"Class":"4","Title":null,"ISSN":null,"Review":false,"Eidtions":null},{"Id":184921,"Class":"4","Title":null,"ISSN":null,"Review":false,"Eidtions":null},{"Id":184924,"Class":"3","Title":null,"ISSN":null,"Review":false,"Eidtions":null},{"Id":184946,"Class":"4","Title":null,"ISSN":null,"Review":false,"Eidtions":null},{"Id":184980,"Class":"4","Title":null,"ISSN":null,"Review":false,"Eidtions":null},{"Id":184985,"Class":"4","Title":null,"ISSN":null,"Review":false,"Eidtions":null},{"Id":184990,"Class":"4","Title":null,"ISSN":null,"Review":false,"Eidtions":null},{"Id":185003,"Class":"4","Title":null,"ISSN":null,"Review":false,"Eidtions":null},{"Id":185008,"Class":"4","Title":null,"ISSN":null,"Review":false,"Eidtions":null},{"Id":185009,"Class":"4","Title":null,"ISSN":null,"Review":false,"Eidtions":null},{"Id":185015,"Class":"4","Title":null,"ISSN":null,"Review":false,"Eidtions":null},{"Id":185017,"Class":"4","Title":null,"ISSN":null,"Review":false,"Eidtions":null},{"Id":185025,"Class":"4","Title":null,"ISSN":null,"Review":false,"Eidtions":null},{"Id":185051,"Class":"4","Title":null,"ISSN":null,"Review":false,"Eidtions":null},{"Id":185052,"Class":"4","Title":null,"ISSN":null,"Review":false,"Eidtions":null},{"Id":185059,"Class":"4","Title":null,"ISSN":null,"Review":false,"Eidtions":null},{"Id":185067,"Class":"4","Title":null,"ISSN":null,"Review":false,"Eidtions":null},{"Id":185112,"Class":"4","Title":null,"ISSN":null,"Review":false,"Eidtions":null},{"Id":185113,"Class":"3","Title":null,"ISSN":null,"Review":false,"Eidtions":null},{"Id":185143,"Class":"4","Title":null,"ISSN":null,"Review":false,"Eidtions":null},{"Id":185166,"Class":"4","Title":null,"ISSN":null,"Review":false,"Eidtions":null},{"Id":185172,"Class":"4","Title":null,"ISSN":null,"Review":false,"Eidtions":null},{"Id":185193,"Class":"4","Title":null,"ISSN":null,"Review":false,"Eidtions":null},{"Id":185195,"Class":"4","Title":null,"ISSN":null,"Review":false,"Eidtions":null},{"Id":185199,"Class":"4","Title":null,"ISSN":null,"Review":false,"Eidtions":null},{"Id":185207,"Class":"4","Title":null,"ISSN":null,"Review":false,"Eidtions":null},{"Id":185212,"Class":"4","Title":null,"ISSN":null,"Review":false,"Eidtions":null},{"Id":185221,"Class":"3","Title":null,"ISSN":null,"Review":false,"Eidtions":null},{"Id":185236,"Class":"4","Title":null,"ISSN":null,"Review":false,"Eidtions":null},{"Id":185241,"Class":"4","Title":null,"ISSN":null,"Review":false,"Eidtions":null},{"Id":185269,"Class":"4","Title":null,"ISSN":null,"Review":false,"Eidtions":null},{"Id":185314,"Class":"3","Title":null,"ISSN":null,"Review":false,"Eidtions":null},{"Id":185323,"Class":"4","Title":null,"ISSN":null,"Review":false,"Eidtions":null},{"Id":185344,"Class":"4","Title":null,"ISSN":null,"Review":false,"Eidtions":null},{"Id":185356,"Class":"4","Title":null,"ISSN":null,"Review":false,"Eidtions":null},{"Id":185360,"Class":"4","Title":null,"ISSN":null,"Review":false,"Eidtions":null},{"Id":185393,"Class":"4","Title":null,"ISSN":null,"Review":false,"Eidtions":null},{"Id":185404,"Class":"4","Title":null,"ISSN":null,"Review":false,"Eidtions":null},{"Id":185408,"Class":"3","Title":null,"ISSN":null,"Review":false,"Eidtions":null},{"Id":185433,"Class":"4","Title":null,"ISSN":null,"Review":false,"Eidtions":null},{"Id":185434,"Class":"4","Title":null,"ISSN":null,"Review":false,"Eidtions":null},{"Id":185448,"Class":"4","Title":null,"ISSN":null,"Review":false,"Eidtions":null},{"Id":185494,"Class":"4","Title":null,"ISSN":null,"Review":false,"Eidtions":null},{"Id":185520,"Class":"3","Title":null,"ISSN":null,"Review":false,"Eidtions":null},{"Id":185525,"Class":"4","Title":null,"ISSN":null,"Review":false,"Eidtions":null},{"Id":185526,"Class":"4","Title":null,"ISSN":null,"Review":false,"Eidtions":null},{"Id":185565,"Class":"4","Title":null,"ISSN":null,"Review":false,"Eidtions":null},{"Id":185567,"Class":"4","Title":null,"ISSN":null,"Review":false,"Eidtions":null},{"Id":185574,"Class":"4","Title":null,"ISSN":null,"Review":false,"Eidtions":null},{"Id":185584,"Class":"4","Title":null,"ISSN":null,"Review":false,"Eidtions":null},{"Id":185609,"Class":"4","Title":null,"ISSN":null,"Review":false,"Eidtions":null},{"Id":185615,"Class":"4","Title":null,"ISSN":null,"Review":false,"Eidtions":null},{"Id":185619,"Class":"4","Title":null,"ISSN":null,"Review":false,"Eidtions":null},{"Id":185629,"Class":"4","Title":null,"ISSN":null,"Review":false,"Eidtions":null},{"Id":185637,"Class":"4","Title":null,"ISSN":null,"Review":false,"Eidtions":null},{"Id":185649,"Class":"4","Title":null,"ISSN":null,"Review":false,"Eidtions":null},{"Id":185664,"Class":"4","Title":null,"ISSN":null,"Review":false,"Eidtions":null},{"Id":185706,"Class":"4","Title":null,"ISSN":null,"Review":false,"Eidtions":null},{"Id":185718,"Class":"4","Title":null,"ISSN":null,"Review":false,"Eidtions":null},{"Id":185724,"Class":"4","Title":null,"ISSN":null,"Review":false,"Eidtions":null},{"Id":185733,"Class":"4","Title":null,"ISSN":null,"Review":false,"Eidtions":null},{"Id":185739,"Class":"4","Title":null,"ISSN":null,"Review":false,"Eidtions":null},{"Id":185752,"Class":"4","Title":null,"ISSN":null,"Review":false,"Eidtions":null},{"Id":185760,"Class":"4","Title":null,"ISSN":null,"Review":false,"Eidtions":null},{"Id":185769,"Class":"4","Title":null,"ISSN":null,"Review":false,"Eidtions":null},{"Id":185772,"Class":"4","Title":null,"ISSN":null,"Review":false,"Eidtions":null},{"Id":185796,"Class":"4","Title":null,"ISSN":null,"Review":false,"Eidtions":null},{"Id":185827,"Class":"4","Title":null,"ISSN":null,"Review":false,"Eidtions":null},{"Id":185831,"Class":"4","Title":null,"ISSN":null,"Review":false,"Eidtions":null},{"Id":185852,"Class":"4","Title":null,"ISSN":null,"Review":false,"Eidtions":null},{"Id":185868,"Class":"4","Title":null,"ISSN":null,"Review":false,"Eidtions":null},{"Id":185879,"Class":"4","Title":null,"ISSN":null,"Review":false,"Eidtions":null},{"Id":185884,"Class":"4","Title":null,"ISSN":null,"Review":false,"Eidtions":null},{"Id":185938,"Class":"4","Title":null,"ISSN":null,"Review":false,"Eidtions":null},{"Id":185947,"Class":"4","Title":null,"ISSN":null,"Review":false,"Eidtions":null},{"Id":185959,"Class":"4","Title":null,"ISSN":null,"Review":false,"Eidtions":null},{"Id":185968,"Class":"4","Title":null,"ISSN":null,"Review":false,"Eidtions":null},{"Id":185975,"Class":"4","Title":null,"ISSN":null,"Review":false,"Eidtions":null},{"Id":185982,"Class":"4","Title":null,"ISSN":null,"Review":false,"Eidtions":null},{"Id":185998,"Class":"4","Title":null,"ISSN":null,"Review":false,"Eidtions":null},{"Id":186033,"Class":"4","Title":null,"ISSN":null,"Review":false,"Eidtions":null},{"Id":186039,"Class":"4","Title":null,"ISSN":null,"Review":false,"Eidtions":null},{"Id":186044,"Class":"4","Title":null,"ISSN":null,"Review":false,"Eidtions":null},{"Id":186063,"Class":"4","Title":null,"ISSN":null,"Review":false,"Eidtions":null},{"Id":186080,"Class":"4","Title":null,"ISSN":null,"Review":false,"Eidtions":null},{"Id":186082,"Class":"4","Title":null,"ISSN":null,"Review":false,"Eidtions":null},{"Id":186117,"Class":"4","Title":null,"ISSN":null,"Review":false,"Eidtions":null},{"Id":186143,"Class":"4","Title":null,"ISSN":null,"Review":false,"Eidtions":null},{"Id":186155,"Class":"4","Title":null,"ISSN":null,"Review":false,"Eidtions":null},{"Id":186162,"Class":"4","Title":null,"ISSN":null,"Review":false,"Eidtions":null},{"Id":186166,"Class":"4","Title":null,"ISSN":null,"Review":false,"Eidtions":null},{"Id":186168,"Class":"4","Title":null,"ISSN":null,"Review":false,"Eidtions":null},{"Id":186192,"Class":"4","Title":null,"ISSN":null,"Review":false,"Eidtions":null},{"Id":186207,"Class":"4","Title":null,"ISSN":null,"Review":false,"Eidtions":null},{"Id":186258,"Class":"4","Title":null,"ISSN":null,"Review":false,"Eidtions":null},{"Id":186267,"Class":"4","Title":null,"ISSN":null,"Review":false,"Eidtions":null},{"Id":186280,"Class":"4","Title":null,"ISSN":null,"Review":false,"Eidtions":null},{"Id":186286,"Class":"4","Title":null,"ISSN":null,"Review":false,"Eidtions":null},{"Id":186313,"Class":"4","Title":null,"ISSN":null,"Review":false,"Eidtions":null},{"Id":186330,"Class":"4","Title":null,"ISSN":null,"Review":false,"Eidtions":null},{"Id":186332,"Class":"4","Title":null,"ISSN":null,"Review":false,"Eidtions":null},{"Id":186336,"Class":"4","Title":null,"ISSN":null,"Review":false,"Eidtions":null},{"Id":186341,"Class":"4","Title":null,"ISSN":null,"Review":false,"Eidtions":null},{"Id":186342,"Class":"4","Title":null,"ISSN":null,"Review":false,"Eidtions":null},{"Id":186366,"Class":"4","Title":null,"ISSN":null,"Review":false,"Eidtions":null},{"Id":186410,"Class":"4","Title":null,"ISSN":null,"Review":false,"Eidtions":null},{"Id":186434,"Class":"4","Title":null,"ISSN":null,"Review":false,"Eidtions":null},{"Id":186463,"Class":"3","Title":null,"ISSN":null,"Review":false,"Eidtions":null},{"Id":186484,"Class":"4","Title":null,"ISSN":null,"Review":false,"Eidtions":null},{"Id":186508,"Class":"4","Title":null,"ISSN":null,"Review":false,"Eidtions":null},{"Id":186540,"Class":"4","Title":null,"ISSN":null,"Review":false,"Eidtions":null},{"Id":186548,"Class":"4","Title":null,"ISSN":null,"Review":false,"Eidtions":null},{"Id":186567,"Class":"4","Title":null,"ISSN":null,"Review":false,"Eidtions":null},{"Id":186568,"Class":"4","Title":null,"ISSN":null,"Review":false,"Eidtions":null},{"Id":186576,"Class":"4","Title":null,"ISSN":null,"Review":false,"Eidtions":null},{"Id":186584,"Class":"4","Title":null,"ISSN":null,"Review":false,"Eidtions":null},{"Id":186588,"Class":"4","Title":null,"ISSN":null,"Review":false,"Eidtions":null},{"Id":186599,"Class":"4","Title":null,"ISSN":null,"Review":false,"Eidtions":null},{"Id":186643,"Class":"3","Title":null,"ISSN":null,"Review":false,"Eidtions":null},{"Id":186658,"Class":"4","Title":null,"ISSN":null,"Review":false,"Eidtions":null},{"Id":186665,"Class":"4","Title":null,"ISSN":null,"Review":false,"Eidtions":null},{"Id":186666,"Class":"4","Title":null,"ISSN":null,"Review":false,"Eidtions":null},{"Id":186685,"Class":"4","Title":null,"ISSN":null,"Review":false,"Eidtions":null},{"Id":186708,"Class":"4","Title":null,"ISSN":null,"Review":false,"Eidtions":null},{"Id":186719,"Class":"4","Title":null,"ISSN":null,"Review":false,"Eidtions":null},{"Id":186725,"Class":"4","Title":null,"ISSN":null,"Review":false,"Eidtions":null},{"Id":186738,"Class":"4","Title":null,"ISSN":null,"Review":false,"Eidtions":null},{"Id":186783,"Class":"4","Title":null,"ISSN":null,"Review":false,"Eidtions":null},{"Id":186789,"Class":"4","Title":null,"ISSN":null,"Review":false,"Eidtions":null},{"Id":186827,"Class":"4","Title":null,"ISSN":null,"Review":false,"Eidtions":null},{"Id":186829,"Class":"4","Title":null,"ISSN":null,"Review":false,"Eidtions":null},{"Id":186834,"Class":"4","Title":null,"ISSN":null,"Review":false,"Eidtions":null},{"Id":186838,"Class":"4","Title":null,"ISSN":null,"Review":false,"Eidtions":null},{"Id":186845,"Class":"4","Title":null,"ISSN":null,"Review":false,"Eidtions":null},{"Id":186848,"Class":"4","Title":null,"ISSN":null,"Review":false,"Eidtions":null},{"Id":186864,"Class":"4","Title":null,"ISSN":null,"Review":false,"Eidtions":null},{"Id":186868,"Class":"4","Title":null,"ISSN":null,"Review":false,"Eidtions":null},{"Id":186876,"Class":"4","Title":null,"ISSN":null,"Review":false,"Eidtions":null},{"Id":186879,"Class":"2","Title":null,"ISSN":null,"Review":false,"Eidtions":null},{"Id":186887,"Class":"4","Title":null,"ISSN":null,"Review":false,"Eidtions":null},{"Id":186890,"Class":"4","Title":null,"ISSN":null,"Review":false,"Eidtions":null},{"Id":186900,"Class":"4","Title":null,"ISSN":null,"Review":false,"Eidtions":null},{"Id":186908,"Class":"4","Title":null,"ISSN":null,"Review":false,"Eidtions":null},{"Id":186909,"Class":"4","Title":null,"ISSN":null,"Review":false,"Eidtions":null},{"Id":186916,"Class":"4","Title":null,"ISSN":null,"Review":false,"Eidtions":null},{"Id":186958,"Class":"4","Title":null,"ISSN":null,"Review":false,"Eidtions":null},{"Id":186960,"Class":"4","Title":null,"ISSN":null,"Review":false,"Eidtions":null},{"Id":186961,"Class":"4","Title":null,"ISSN":null,"Review":false,"Eidtions":null},{"Id":186964,"Class":"4","Title":null,"ISSN":null,"Review":false,"Eidtions":null},{"Id":186987,"Class":"4","Title":null,"ISSN":null,"Review":false,"Eidtions":null},{"Id":187019,"Class":"4","Title":null,"ISSN":null,"Review":false,"Eidtions":null},{"Id":187046,"Class":"4","Title":null,"ISSN":null,"Review":false,"Eidtions":null},{"Id":187048,"Class":"4","Title":null,"ISSN":null,"Review":false,"Eidtions":null},{"Id":187073,"Class":"4","Title":null,"ISSN":null,"Review":false,"Eidtions":null},{"Id":187077,"Class":"4","Title":null,"ISSN":null,"Review":false,"Eidtions":null},{"Id":187078,"Class":"4","Title":null,"ISSN":null,"Review":false,"Eidtions":null},{"Id":187079,"Class":"4","Title":null,"ISSN":null,"Review":false,"Eidtions":null},{"Id":187124,"Class":"4","Title":null,"ISSN":null,"Review":false,"Eidtions":null},{"Id":187125,"Class":"4","Title":null,"ISSN":null,"Review":false,"Eidtions":null},{"Id":187144,"Class":"4","Title":null,"ISSN":null,"Review":false,"Eidtions":null},{"Id":187224,"Class":"4","Title":null,"ISSN":null,"Review":false,"Eidtions":null},{"Id":187244,"Class":"4","Title":null,"ISSN":null,"Review":false,"Eidtions":null},{"Id":187245,"Class":"4","Title":null,"ISSN":null,"Review":false,"Eidtions":null},{"Id":187258,"Class":"4","Title":null,"ISSN":null,"Review":false,"Eidtions":null},{"Id":187286,"Class":"4","Title":null,"ISSN":null,"Review":false,"Eidtions":null},{"Id":187303,"Class":"4","Title":null,"ISSN":null,"Review":false,"Eidtions":null},{"Id":187307,"Class":"4","Title":null,"ISSN":null,"Review":false,"Eidtions":null},{"Id":187332,"Class":"4","Title":null,"ISSN":null,"Review":false,"Eidtions":null},{"Id":187336,"Class":"4","Title":null,"ISSN":null,"Review":false,"Eidtions":null},{"Id":187358,"Class":"4","Title":null,"ISSN":null,"Review":false,"Eidtions":null},{"Id":187361,"Class":"4","Title":null,"ISSN":null,"Review":false,"Eidtions":null},{"Id":187381,"Class":"4","Title":null,"ISSN":null,"Review":false,"Eidtions":null},{"Id":187416,"Class":"4","Title":null,"ISSN":null,"Review":false,"Eidtions":null},{"Id":187476,"Class":"4","Title":null,"ISSN":null,"Review":false,"Eidtions":null},{"Id":187500,"Class":"4","Title":null,"ISSN":null,"Review":false,"Eidtions":null},{"Id":187501,"Class":"4","Title":null,"ISSN":null,"Review":false,"Eidtions":null},{"Id":187502,"Class":"4","Title":null,"ISSN":null,"Review":false,"Eidtions":null},{"Id":187518,"Class":"4","Title":null,"ISSN":null,"Review":false,"Eidtions":null},{"Id":187522,"Class":"4","Title":null,"ISSN":null,"Review":false,"Eidtions":null},{"Id":187537,"Class":"4","Title":null,"ISSN":null,"Review":false,"Eidtions":null},{"Id":187551,"Class":"4","Title":null,"ISSN":null,"Review":false,"Eidtions":null},{"Id":187552,"Class":"4","Title":null,"ISSN":null,"Review":false,"Eidtions":null},{"Id":187560,"Class":"4","Title":null,"ISSN":null,"Review":false,"Eidtions":null},{"Id":187573,"Class":"4","Title":null,"ISSN":null,"Review":false,"Eidtions":null},{"Id":187582,"Class":"4","Title":null,"ISSN":null,"Review":false,"Eidtions":null},{"Id":187603,"Class":"4","Title":null,"ISSN":null,"Review":false,"Eidtions":null},{"Id":187649,"Class":"4","Title":null,"ISSN":null,"Review":false,"Eidtions":null},{"Id":187673,"Class":"4","Title":null,"ISSN":null,"Review":false,"Eidtions":null},{"Id":187702,"Class":"4","Title":null,"ISSN":null,"Review":false,"Eidtions":null},{"Id":187767,"Class":"4","Title":null,"ISSN":null,"Review":false,"Eidtions":null},{"Id":187818,"Class":"4","Title":null,"ISSN":null,"Review":false,"Eidtions":null},{"Id":187885,"Class":"4","Title":null,"ISSN":null,"Review":false,"Eidtions":null},{"Id":187902,"Class":"4","Title":null,"ISSN":null,"Review":false,"Eidtions":null},{"Id":187910,"Class":"4","Title":null,"ISSN":null,"Review":false,"Eidtions":null},{"Id":187920,"Class":"4","Title":null,"ISSN":null,"Review":false,"Eidtions":null},{"Id":187925,"Class":"4","Title":null,"ISSN":null,"Review":false,"Eidtions":null},{"Id":187929,"Class":"4","Title":null,"ISSN":null,"Review":false,"Eidtions":null},{"Id":187931,"Class":"4","Title":null,"ISSN":null,"Review":false,"Eidtions":null},{"Id":187939,"Class":"4","Title":null,"ISSN":null,"Review":false,"Eidtions":null},{"Id":187955,"Class":"4","Title":null,"ISSN":null,"Review":false,"Eidtions":null},{"Id":187965,"Class":"4","Title":null,"ISSN":null,"Review":false,"Eidtions":null},{"Id":187971,"Class":"4","Title":null,"ISSN":null,"Review":false,"Eidtions":null},{"Id":188006,"Class":"4","Title":null,"ISSN":null,"Review":false,"Eidtions":null},{"Id":188025,"Class":"4","Title":null,"ISSN":null,"Review":false,"Eidtions":null},{"Id":188045,"Class":"4","Title":null,"ISSN":null,"Review":false,"Eidtions":null},{"Id":188046,"Class":"4","Title":null,"ISSN":null,"Review":false,"Eidtions":null},{"Id":188052,"Class":"4","Title":null,"ISSN":null,"Review":false,"Eidtions":null},{"Id":188089,"Class":"4","Title":null,"ISSN":null,"Review":false,"Eidtions":null},{"Id":188106,"Class":"4","Title":null,"ISSN":null,"Review":false,"Eidtions":null},{"Id":188144,"Class":"4","Title":null,"ISSN":null,"Review":false,"Eidtions":null},{"Id":188149,"Class":"4","Title":null,"ISSN":null,"Review":false,"Eidtions":null},{"Id":188151,"Class":"4","Title":null,"ISSN":null,"Review":false,"Eidtions":null},{"Id":188156,"Class":"4","Title":null,"ISSN":null,"Review":false,"Eidtions":null},{"Id":188169,"Class":"4","Title":null,"ISSN":null,"Review":false,"Eidtions":null},{"Id":188190,"Class":"4","Title":null,"ISSN":null,"Review":false,"Eidtions":null},{"Id":188212,"Class":"4","Title":null,"ISSN":null,"Review":false,"Eidtions":null},{"Id":188230,"Class":"4","Title":null,"ISSN":null,"Review":false,"Eidtions":null},{"Id":188254,"Class":"4","Title":null,"ISSN":null,"Review":false,"Eidtions":null},{"Id":188255,"Class":"4","Title":null,"ISSN":null,"Review":false,"Eidtions":null},{"Id":188272,"Class":"4","Title":null,"ISSN":null,"Review":false,"Eidtions":null},{"Id":188275,"Class":"4","Title":null,"ISSN":null,"Review":false,"Eidtions":null},{"Id":188284,"Class":"4","Title":null,"ISSN":null,"Review":false,"Eidtions":null},{"Id":188287,"Class":"4","Title":null,"ISSN":null,"Review":false,"Eidtions":null},{"Id":188295,"Class":"4","Title":null,"ISSN":null,"Review":false,"Eidtions":null},{"Id":188305,"Class":"4","Title":null,"ISSN":null,"Review":false,"Eidtions":null},{"Id":188309,"Class":"4","Title":null,"ISSN":null,"Review":false,"Eidtions":null},{"Id":188332,"Class":"4","Title":null,"ISSN":null,"Review":false,"Eidtions":null},{"Id":188359,"Class":"4","Title":null,"ISSN":null,"Review":false,"Eidtions":null},{"Id":188362,"Class":"4","Title":null,"ISSN":null,"Review":false,"Eidtions":null},{"Id":188373,"Class":"4","Title":null,"ISSN":null,"Review":false,"Eidtions":null},{"Id":188380,"Class":"4","Title":null,"ISSN":null,"Review":false,"Eidtions":null},{"Id":188392,"Class":"4","Title":null,"ISSN":null,"Review":false,"Eidtions":null},{"Id":188397,"Class":"4","Title":null,"ISSN":null,"Review":false,"Eidtions":null},{"Id":188401,"Class":"4","Title":null,"ISSN":null,"Review":false,"Eidtions":null},{"Id":188409,"Class":"4","Title":null,"ISSN":null,"Review":false,"Eidtions":null},{"Id":188432,"Class":"4","Title":null,"ISSN":null,"Review":false,"Eidtions":null},{"Id":188446,"Class":"4","Title":null,"ISSN":null,"Review":false,"Eidtions":null},{"Id":188509,"Class":"4","Title":null,"ISSN":null,"Review":false,"Eidtions":null},{"Id":188510,"Class":"4","Title":null,"ISSN":null,"Review":false,"Eidtions":null},{"Id":188524,"Class":"4","Title":null,"ISSN":null,"Review":false,"Eidtions":null},{"Id":188541,"Class":"3","Title":null,"ISSN":null,"Review":false,"Eidtions":null},{"Id":188550,"Class":"4","Title":null,"ISSN":null,"Review":false,"Eidtions":null},{"Id":188553,"Class":"4","Title":null,"ISSN":null,"Review":false,"Eidtions":null},{"Id":188582,"Class":"4","Title":null,"ISSN":null,"Review":false,"Eidtions":null},{"Id":188647,"Class":"4","Title":null,"ISSN":null,"Review":false,"Eidtions":null},{"Id":188664,"Class":"4","Title":null,"ISSN":null,"Review":false,"Eidtions":null},{"Id":188665,"Class":"4","Title":null,"ISSN":null,"Review":false,"Eidtions":null},{"Id":188676,"Class":"4","Title":null,"ISSN":null,"Review":false,"Eidtions":null},{"Id":188689,"Class":"4","Title":null,"ISSN":null,"Review":false,"Eidtions":null},{"Id":188701,"Class":"4","Title":null,"ISSN":null,"Review":false,"Eidtions":null},{"Id":188719,"Class":"4","Title":null,"ISSN":null,"Review":false,"Eidtions":null},{"Id":188762,"Class":"4","Title":null,"ISSN":null,"Review":false,"Eidtions":null},{"Id":188784,"Class":"4","Title":null,"ISSN":null,"Review":false,"Eidtions":null},{"Id":188800,"Class":"4","Title":null,"ISSN":null,"Review":false,"Eidtions":null}]